[
  {
    "_id": { "$oid": "6936d957fbb35077593b1223" },
    "name": "Sườn non heo giá tốt tại Bách hoá XANH",
    "sku": "suon-non-heo-1kg",
    "image": "https://cdnv2.tgdd.vn/bhx-static/bhx/Products/Images/8781/226856/bhx/suon-non-heo-1kg_202511031615229428.jpg",
    "category": [{ "$oid": "6908d50bce3345081ade433e" }],
    "unit": "1 Khay",
    "unitSize": 1,
    "stock": 19,
    "price": 60300,
    "discount": 10,
    "description": "Mô tả sản phẩm của hệ thông bán hàng.",
    "subcategory": [{ "$oid": "6908d541ce3345081ade434c" }]
  },
  {
    "_id": { "$oid": "6936d957fbb35077593b1224" },
    "name": "Xà lách thủy tinh thủy canh tươi ngon tại Bách hoá XANH",
    "sku": "xa-lach-thuy-tinh-thuy-canh-cay-tu-230g",
    "image": "https://cdnv2.tgdd.vn/bhx-static/bhx/Products/Images/8820/303824/bhx/xa-lach-thuy-tinh-thuy-canh-cay-tu-230g_202505142330545221.jpg",
    "category": [{ "$oid": "6908d4e8ce3345081ade433b" }],
    "unit": "Bó",
    "unitSize": 0.23,
    "stock": 6,
    "price": 16000,
    "discount": 10,
    "description": "Mô tả sản phẩm của hệ thông bán hàng.",
    "subcategory": [{ "$oid": "6908d5bece3345081ade4366" }]
  },
  {
    "_id": { "$oid": "6936d957fbb35077593b1225" },
    "name": "Thịt heo xay CP 100g tại Bách hoá XANH",
    "sku": "thit-heo-xay-cp-100g",
    "image": "https://cdnv2.tgdd.vn/bhx-static/bhx/Products/Images/8781/333450/bhx/thit-heo-xay-cp-100g_202511041615391940.jpg",
    "category": [{ "$oid": "6908d50bce3345081ade433e" }],
    "unit": "Túi",
    "stock": 23,
    "price": 12500,
    "discount": 5,
    "description": "Mô tả sản phẩm của hệ thông bán hàng.",
    "subcategory": [{ "$oid": "6908d541ce3345081ade434c" }]
  },
  {
    "_id": { "$oid": "6936d957fbb35077593b1226" },
    "name": "Khoai tây giá tốt tại Bách hoá XANH",
    "sku": "khoai-tay-500g",
    "image": "https://cdnv2.tgdd.vn/bhx-static/bhx/Products/Images/8785/230468/bhx/khoai-tay-500g_202504241414094775.jpg",
    "category": [{ "$oid": "6908d4e8ce3345081ade433b" }],
    "unit": "Túi",
    "unitSize": 0.5,
    "stock": 17,
    "price": 15000,
    "discount": 10,
    "description": "Mô tả sản phẩm của hệ thông bán hàng.",
    "subcategory": [{ "$oid": "6936d01e9bca55d5bca3016f" }]
  },
  {
    "_id": { "$oid": "6936d957fbb35077593b1227" },
    "name": "Bắp mỹ giòn ngọt giá tốt tại Bách hoá XANH",
    "sku": "bap-my-trai-tu-300g-tro-len-3-trai",
    "image": "https://cdnv2.tgdd.vn/bhx-static/bhx/Products/Images/8785/358354/bhx/bap-my-trai-tu-300g-tro-len-3-trai_202510241003453573.jpg",
    "category": [{ "$oid": "6908d4e8ce3345081ade433b" }],
    "unit": "Túi",
    "unitSize": 3,
    "stock": 8,
    "price": 22500,
    "discount": 0,
    "description": "Mô tả sản phẩm của hệ thông bán hàng.",
    "subcategory": [{ "$oid": "6936d01e9bca55d5bca3016f" }]
  },
  {
    "_id": { "$oid": "6936d957fbb35077593b1228" },
    "name": "Má đùi gà cắt sẵn giá tốt tại Bách hoá XANH",
    "sku": "ma-dui-ga-cat-san-1kg",
    "image": "https://cdnv2.tgdd.vn/bhx-static/bhx/Products/Images/8790/226888/bhx/ma-dui-ga-cat-san-1kg_202504121721043296.jpg",
    "category": [{ "$oid": "6908d50bce3345081ade433e" }],
    "subcategory": [{ "$oid": "6911eb361141be8e94c27cf8" }],
    "unit": "Khay",
    "unitSize": 1,
    "stock": 17,
    "price": 36800,
    "discount": 0,
    "description": "Mô tả sản phẩm của hệ thông bán hàng."
  },
  {
    "_id": { "$oid": "6936d957fbb35077593b1229" },
    "name": "Rau mồng tơi gói 300g tươi ngon tại Bách hoá XANH",
    "sku": "rau-mong-toi-goi-300g",
    "image": "https://cdnv2.tgdd.vn/bhx-static/bhx/Products/Images/8820/298825/bhx/rau-mong-toi-goi-300g_202505240805208451.jpg",
    "category": [{ "$oid": "6908d4e8ce3345081ade433b" }],
    "unit": "TúTúi",
    "unitSize": 0.3,
    "stock": 3,
    "price": 16900,
    "discount": 0,
    "description": "Mô tả sản phẩm của hệ thông bán hàng.",
    "subcategory": [{ "$oid": "6908d5bece3345081ade4366" }]
  },
  {
    "_id": { "$oid": "6936d957fbb35077593b122a" },
    "name": "Chân giò heo C.P 300g tại Bách hoá XANH",
    "sku": "chan-gio-heo-cp-300g",
    "image": "https://cdnv2.tgdd.vn/bhx-static/bhx/Products/Images/8781/344660/bhx/chan-gio-heo-cp-300g_202511031616579971.jpg",
    "category": [{ "$oid": "6908d50bce3345081ade433e" }],
    "unit": "Túi",
    "unitSize": 0.3,
    "stock": 30,
    "price": 26700,
    "discount": 5,
    "description": "Mô tả sản phẩm của hệ thông bán hàng.",
    "subcategory": [{ "$oid": "6908d541ce3345081ade434c" }]
  },
  {
    "_id": { "$oid": "6936d957fbb35077593b122b" },
    "name": "2 hộp trứng vịt hộp 10 quả giá tốt tại Bách hoá XANH",
    "sku": "2-hop-trung-vit-hop-10-qua-tu-600g-700g-giao-ngau-nhien-thuong-hieu",
    "image": [
      "https://cdnv2.tgdd.vn/bhx-static/bhx/Products/Images/8783/358508/bhx/trung-vit-hop-10-qua-tu-600g-700g-giao-ngau-nhien-thuong-hieu-clone_202510301504309050.jpg"
    ],
    "category": [{ "$oid": "6908d50bce3345081ade433e" }],
    "subcategory": [{ "$oid": "6908d575ce3345081ade4357" }],
    "unit": "Túi",
    "unitSize": 0.3,
    "stock": 17,
    "price": 68000,
    "discount": 0,
    "description": "Mô tả sản phẩm của hệ thông bán hàng.",
    "more_details": {},
    "subCategory": [{ "$oid": "6908d575ce3345081ade4357" }],
    "updatedAt": { "$date": "2025-12-08T14:06:57.282Z" }
  },
  {
    "_id": { "$oid": "6936d957fbb35077593b122c" },
    "name": "Rau dền tươi xanh khoảng 300g giá tốt tại Bách hoá XANH",
    "sku": "rau-den-baby-goi-300g",
    "image": "https://cdnv2.tgdd.vn/bhx-static/bhx/Products/Images/8820/223344/bhx/rau-den-baby-goi-300g_202509050855262233.jpg",
    "category": [{ "$oid": "6908d4e8ce3345081ade433b" }],
    "unit": "Túi",
    "unitSize": 0.3,
    "stock": 30,
    "price": 16900,
    "discount": 10,
    "description": "Mô tả sản phẩm của hệ thông bán hàng.",
    "subcategory": [{ "$oid": "6908d5bece3345081ade4366" }]
  },
  {
    "_id": { "$oid": "6936d957fbb35077593b122d" },
    "name": "Cá nục sốt ớt chua ngọt hộp 155g giá tốt tại Bách hoá XANH",
    "sku": "ca-nuc-sot-ot-chua-ngot-sea-crown-hop-155g",
    "image": "https://cdnv2.tgdd.vn/bhx-static/bhx/Products/Images/3237/149419/bhx/149419_202411121511024811.png",
    "category": [{ "$oid": "6936d53bfc65c6985f8c5770" }],
    "subcategory": [{ "$oid": "6936d555fc65c6985f8c5780" }],
    "unit": "Túi",
    "unitSize": 0.3,
    "stock": 3,
    "price": null,
    "discount": 10,
    "description": "Mô tả sản phẩm của hệ thông bán hàng."
  },
  {
    "_id": { "$oid": "6936d957fbb35077593b122e" },
    "name": "Thùng 30 gói mì sợi phở Gấu Đỏ 63g giá tốt tại Bách hoá XANH",
    "sku": "mi-gau-do-vi-ga-soi-pho-goi-64g-thung-30-goi",
    "image": "https://www.bachhoaxanh.com/thung-30-goi-mi-ga-soi-pho-gau-do-63g-202407121505166916.jpg",
    "category": [{ "$oid": "6908d33cce3345081ade4321" }],
    "unit": "Túi",
    "unitSize": 0.3,
    "stock": 22,
    "price": 86000,
    "discount": 0,
    "description": "Mô tả sản phẩm của hệ thông bán hàng.",
    "subcategory": [{ "$oid": "6908d8bcce3345081ade43d3" }]
  },
  {
    "_id": { "$oid": "6936d957fbb35077593b122f" },
    "name": "Xoài keo giòn túi 1kg (2-4 trái) giá tốt tại Bách hoá XANH",
    "sku": "xoai-keo-tui-1kg",
    "image": "https://cdnv2.tgdd.vn/bhx-static/bhx/Products/Images/8788/233096/bhx/xoai-keo-tui-1kg_202512031518455251.jpg",
    "category": [{ "$oid": "6908d4e8ce3345081ade433b" }],
    "unit": "Túi",
    "unitSize": 0.3,
    "stock": 19,
    "price": 19900,
    "discount": 10,
    "description": "Mô tả sản phẩm của hệ thông bán hàng.",
    "subcategory": [{ "$oid": "6908d5b5ce3345081ade4362" }]
  },
  {
    "_id": { "$oid": "6936d957fbb35077593b1230" },
    "name": "Xoài tứ quý giá tốt tại Bách hoá XANH",
    "sku": "xoai-tu-quy1kg",
    "image": "https://cdnv2.tgdd.vn/bhx-static/bhx/Products/Images/8788/234063/bhx/xoai-tu-quy1kg_202504231027022875.jpg",
    "category": [{ "$oid": "6908d4e8ce3345081ade433b" }],
    "unit": "Túi",
    "unitSize": 0.3,
    "stock": 3,
    "price": 26200,
    "discount": 10,
    "description": "Mô tả sản phẩm của hệ thông bán hàng.",
    "subcategory": [{ "$oid": "6908d5b5ce3345081ade4362" }]
  },
  {
    "_id": { "$oid": "6936d957fbb35077593b1231" },
    "name": "Chân gà giá tốt tại Bách hoá XANH",
    "sku": "chan-ga-1kg",
    "image": "https://cdnv2.tgdd.vn/bhx-static/bhx/Products/Images/8790/226952/bhx/chan-ga-1kg_202504121632142513.jpg",
    "category": [{ "$oid": "6908d50bce3345081ade433e" }],
    "subcategory": [{ "$oid": "6911eb361141be8e94c27cf8" }],
    "unit": "Túi",
    "unitSize": 0.3,
    "stock": 22,
    "price": 25480,
    "discount": 5,
    "description": "Mô tả sản phẩm của hệ thông bán hàng."
  },
  {
    "_id": { "$oid": "6936d957fbb35077593b1232" },
    "name": "Sườn cốt lết C.P giá tốt tại Bách hoá XANH",
    "sku": "suon-cot-let-1kg",
    "image": "https://cdnv2.tgdd.vn/bhx-static/bhx/Products/Images/8781/226937/bhx/suon-cot-let-1kg_202511041611031577.jpg",
    "category": [{ "$oid": "6908d50bce3345081ade433e" }],
    "unit": "Túi",
    "unitSize": 0.3,
    "stock": 26,
    "price": 29700,
    "discount": 5,
    "description": "Mô tả sản phẩm của hệ thông bán hàng.",
    "subcategory": [{ "$oid": "6908d541ce3345081ade434c" }]
  },
  {
    "_id": { "$oid": "6936d957fbb35077593b1233" },
    "name": "Canh củ thập cẩm tôm tại Bách hoá XANH",
    "sku": "canh-cu-thap-cam-tom-khay-350g",
    "image": "https://cdnv2.tgdd.vn/bhx-static/bhx/Products/Images/12718/341810/bhx/canh-cu-thap-cam-tom-khay-350g_202508021534247626.jpg",
    "category": [{ "$oid": "6908d4e8ce3345081ade433b" }],
    "unit": "Túi",
    "unitSize": 0.3,
    "stock": 16,
    "price": 42000,
    "discount": 10,
    "description": "Mô tả sản phẩm của hệ thông bán hàng.",
    "subcategory": [{ "$oid": "6936d01e9bca55d5bca3016f" }]
  },
  {
    "_id": { "$oid": "6936d957fbb35077593b1234" },
    "name": "Cải thìa giá tốt tại Bách hoá XANH",
    "sku": "cai-thia-da-lat-1kg",
    "image": "https://cdnv2.tgdd.vn/bhx-static/bhx/Products/Images/8820/238556/bhx/cai-thia-da-lat-1kg_202505101101090367.jpg",
    "category": [{ "$oid": "6908d4e8ce3345081ade433b" }],
    "unit": "Túi",
    "unitSize": 0.3,
    "stock": 1,
    "price": 16900,
    "discount": 0,
    "description": "Mô tả sản phẩm của hệ thông bán hàng.",
    "subcategory": [{ "$oid": "6908d5bece3345081ade4366" }]
  },
  {
    "_id": { "$oid": "6936d957fbb35077593b1235" },
    "name": "Trứng gà ta hộp 6 quả chất lượng tại Bách hoá XANH",
    "sku": "trung-ga-ta-hop-6-qua",
    "image": "https://cdnv2.tgdd.vn/bhx-static/bhx/Products/Images/8783/311111/bhx/trung-ga-ta-hop-6-qua_202509301124032388.jpg",
    "category": [{ "$oid": "6908d50bce3345081ade433e" }],
    "subcategory": [{ "$oid": "6908d575ce3345081ade4357" }],
    "unit": "Túi",
    "unitSize": 0.3,
    "stock": 3,
    "price": 27000,
    "discount": 5,
    "description": "Mô tả sản phẩm của hệ thông bán hàng."
  },
  {
    "_id": { "$oid": "6936d957fbb35077593b1236" },
    "name": "Mì cay Nissin vị thái tôm yum 70g tại Bách hóa XANH",
    "sku": "mi-cay-nissin-vi-thai-tom-yum-70g",
    "image": "https://cdnv2.tgdd.vn/bhx-static/bhx/Products/Images/2565/332669/bhx/332669-2_202412040008244269.jpg",
    "category": [{ "$oid": "6908d33cce3345081ade4321" }],
    "unit": "Túi",
    "unitSize": 0.3,
    "stock": 25,
    "price": 5000,
    "discount": 10,
    "description": "Mô tả sản phẩm của hệ thông bán hàng.",
    "subcategory": [{ "$oid": "6908d8bcce3345081ade43d3" }]
  },
  {
    "_id": { "$oid": "6936d957fbb35077593b1237" },
    "name": "Bò bít tết Úc Mr.T khay 200g giá tốt tại Bách Hoá XANH",
    "sku": "bo-bit-tet-uc-mrt-khay-200g",
    "image": "https://cdnv2.tgdd.vn/bhx-static/bhx/Products/Images/8139/326008/bhx/bo-bit-tet-uc-mrt-khay-200g_202508070913098866.jpg",
    "category": [{ "$oid": "6908d50bce3345081ade433e" }],
    "unit": "Túi",
    "unitSize": 0.3,
    "stock": 19,
    "price": 99000,
    "discount": 10,
    "description": "Mô tả sản phẩm của hệ thông bán hàng.",
    "subcategory": [{ "$oid": "6911ed3f1141be8e94c27d4c" }]
  },
  {
    "_id": { "$oid": "6936d957fbb35077593b1238" },
    "name": "Cá trích sốt cà chua Lil155g giá tốt tại Bách hoá XANH",
    "sku": "ca-trich-sot-ca-lilly-hop-155g",
    "image": "https://cdnv2.tgdd.vn/bhx-static/bhx/Products/Images/3237/83360/bhx/83360_202411121507012336.png",
    "category": [{ "$oid": "6936d53bfc65c6985f8c5770" }],
    "subcategory": [{ "$oid": "6936d555fc65c6985f8c5780" }],
    "unit": "Túi",
    "unitSize": 0.3,
    "stock": 21,
    "price": null,
    "discount": 10,
    "description": "Mô tả sản phẩm của hệ thông bán hàng."
  },
  {
    "_id": { "$oid": "6936d957fbb35077593b1239" },
    "name": "Đùi bò Việt Nam giá tốt tại Bách hoá XANH",
    "sku": "dui-bo-viet-nam-tui-1kg",
    "image": "https://cdnv2.tgdd.vn/bhx-static/bhx/Products/Images/8139/233807/bhx/dui-bo-viet-nam-tui-1kg_202511041108393794.jpg",
    "category": [{ "$oid": "6908d50bce3345081ade433e" }],
    "unit": "Túi",
    "unitSize": 0.3,
    "stock": 14,
    "price": 56400,
    "discount": 0,
    "description": "Mô tả sản phẩm của hệ thông bán hàng.",
    "subcategory": [{ "$oid": "6911ed3f1141be8e94c27d4c" }]
  },
  {
    "_id": { "$oid": "6936d957fbb35077593b123a" },
    "name": "Bí đỏ tròn 500g tươi ngon, giá cả cực tốt tại Bách hoá XANH",
    "sku": "bi-do-tron-500g",
    "image": "https://cdnv2.tgdd.vn/bhx-static/bhx/Products/Images/8785/341597/bhx/bi-do-tron-500g_202507281639218906.jpg",
    "category": [{ "$oid": "6908d4e8ce3345081ade433b" }],
    "unit": "Túi",
    "unitSize": 0.3,
    "stock": 9,
    "price": 10500,
    "discount": 5,
    "description": "Mô tả sản phẩm của hệ thông bán hàng.",
    "subcategory": [{ "$oid": "6936d01e9bca55d5bca3016f" }]
  },
  {
    "_id": { "$oid": "6936d957fbb35077593b123b" },
    "name": "Cá nục làm sạch giá rẻ tại Bách hoá XANH",
    "sku": "ca-nuc-lam-sach-500g",
    "image": "https://cdnv2.tgdd.vn/bhx-static/bhx/Products/Images/8782/339822/bhx/ca-nuc-lam-sach-500g_202506260946496333.jpg",
    "category": [{ "$oid": "6908d50bce3345081ade433e" }],
    "unit": "Túi",
    "unitSize": 0.3,
    "stock": 14,
    "price": 49500,
    "discount": 5,
    "description": "Mô tả sản phẩm của hệ thông bán hàng.",
    "subcategory": [{ "$oid": "6911ef161141be8e94c27e05" }]
  },
  {
    "_id": { "$oid": "6936d957fbb35077593b123c" },
    "name": "Cá nục xốt cà Thai Ship 155g | Bách hoá XANH online",
    "sku": "ca-nuc-xot-ca-thai-ship-155g",
    "image": "https://cdnv2.tgdd.vn/bhx-static/bhx/Products/Images/3237/332152/bhx/thiet-ke-chua-co-ten-2024-12-02t100649297_202412021006552153.jpg",
    "category": [{ "$oid": "6936d53bfc65c6985f8c5770" }],
    "subcategory": [{ "$oid": "6936d555fc65c6985f8c5780" }],
    "unit": "Túi",
    "unitSize": 0.3,
    "stock": 21,
    "price": 15000,
    "discount": 5,
    "description": "Mô tả sản phẩm của hệ thông bán hàng."
  },
  {
    "_id": { "$oid": "6936d957fbb35077593b123d" },
    "name": "Cà chua giá tốt tại Bách hoá XANH",
    "sku": "ca-chua-1kg",
    "image": "https://cdnv2.tgdd.vn/bhx-static/bhx/Products/Images/8785/230449/bhx/ca-chua-1kg_202504140839243888.jpg",
    "category": [{ "$oid": "6908d4e8ce3345081ade433b" }],
    "unit": "Túi",
    "unitSize": 0.3,
    "stock": 10,
    "price": 32500,
    "discount": 10,
    "description": "Mô tả sản phẩm của hệ thông bán hàng.",
    "subcategory": [{ "$oid": "6936d01e9bca55d5bca3016f" }]
  },
  {
    "_id": { "$oid": "6936d957fbb35077593b123e" },
    "name": "Cá ngừ xốt tương Tuna Việt Nam155g giá tốt tại Bách hoá XANH",
    "sku": "ca-ngu-xot-tuong-tuna-viet-nam-hop-155g",
    "image": "https://cdnv2.tgdd.vn/bhx-static/bhx/Products/Images/3237/252844/bhx/252844_202411121548223008.png",
    "category": [{ "$oid": "6936d53bfc65c6985f8c5770" }],
    "subcategory": [{ "$oid": "6936d555fc65c6985f8c5780" }],
    "unit": "Túi",
    "unitSize": 0.3,
    "stock": 16,
    "price": 12500,
    "discount": 0,
    "description": "Mô tả sản phẩm của hệ thông bán hàng."
  },
  {
    "_id": { "$oid": "6936d957fbb35077593b123f" },
    "name": "Dưa lưới tròn ruột cam trái giá tốt tại Bách hoá XANH",
    "sku": "dua-luoi-tron-ruot-cam-1kg",
    "image": "https://cdnv2.tgdd.vn/bhx-static/bhx/Products/Images/8788/226931/bhx/dua-luoi-tron-ruot-cam-1kg_202508180928122619.jpg",
    "category": [{ "$oid": "6908d4e8ce3345081ade433b" }],
    "unit": "Túi",
    "unitSize": 0.3,
    "stock": 6,
    "price": 53300,
    "discount": 10,
    "description": "Mô tả sản phẩm của hệ thông bán hàng.",
    "subcategory": [{ "$oid": "6908d5b5ce3345081ade4362" }]
  },
  {
    "_id": { "$oid": "6936d957fbb35077593b1240" },
    "name": "Trứng cút hộp 30 tươi mới, giá tốt tại Bách hóa XANH",
    "sku": "trung-cut-hop-30",
    "image": "https://cdnv2.tgdd.vn/bhx-static/bhx/Products/Images/8783/311101/bhx/trung-cut-hop-30_202509301108172327.jpg",
    "category": [{ "$oid": "6908d50bce3345081ade433e" }],
    "subcategory": [{ "$oid": "6908d575ce3345081ade4357" }],
    "unit": "Túi",
    "unitSize": 0.3,
    "stock": 3,
    "price": 27000,
    "discount": 5,
    "description": "Mô tả sản phẩm của hệ thông bán hàng."
  },
  {
    "_id": { "$oid": "6936d957fbb35077593b1241" },
    "name": "Cá diêu hồng làm sạch giá rẻ tại Bách hoá XANH",
    "sku": "ca-dieu-hong-lam-sach-nguyen-con",
    "image": "https://cdnv2.tgdd.vn/bhx-static/bhx/Products/Images/8782/309731/bhx/ca-dieu-hong-lam-sach-nguyen-con_202505252312056234.jpg",
    "category": [{ "$oid": "6908d50bce3345081ade433e" }],
    "unit": "Túi",
    "unitSize": 0.3,
    "stock": 17,
    "price": 47000,
    "discount": 5,
    "description": "Mô tả sản phẩm của hệ thông bán hàng.",
    "subcategory": [{ "$oid": "6911ef161141be8e94c27e05" }]
  },
  {
    "_id": { "$oid": "6936d957fbb35077593b1242" },
    "name": "24 mì khoai tây Cung Đình tôm 65g giá tốt tại Bách hoá XANH",
    "sku": "mi-ly-cung-dinh-lau-tom-chua-cay-65g-thung-24-ly",
    "image": "https://www.bachhoaxanh.com/thung-24-ly-mi-khoai-tay-cung-dinh-lau-tom-chua-cay-65g-202308160919559214.jpg",
    "category": [{ "$oid": "6908d33cce3345081ade4321" }],
    "unit": "Túi",
    "unitSize": 0.3,
    "stock": 1,
    "price": 207000,
    "discount": 10,
    "description": "Mô tả sản phẩm của hệ thông bán hàng.",
    "subcategory": [{ "$oid": "6908d8bcce3345081ade43d3" }]
  },
  {
    "_id": { "$oid": "6936d957fbb35077593b1243" },
    "name": "Cá nục sốt cà cay Sea Crown 155g giá tốt tại Bách hoá XANH",
    "sku": "ca-nuc-sot-ca-155gam",
    "image": "https://cdnv2.tgdd.vn/bhx-static/bhx/Products/Images/3237/83380/bhx/83380_202411121507302026.png",
    "category": [{ "$oid": "6936d53bfc65c6985f8c5770" }],
    "subcategory": [{ "$oid": "6936d555fc65c6985f8c5780" }],
    "unit": "Túi",
    "unitSize": 0.3,
    "stock": 14,
    "price": 8000,
    "discount": 5,
    "description": "Mô tả sản phẩm của hệ thông bán hàng."
  },
  {
    "_id": { "$oid": "6936d957fbb35077593b1244" },
    "name": "Sườn cốt lết heo làm sạch 500g giá tốt tại Bách hoá XANH",
    "sku": "suon-cot-let-tui-500g",
    "image": "https://cdnv2.tgdd.vn/bhx-static/bhx/Products/Images/8781/226943/bhx/suon-cot-let-tui-500g_202511041611101668.jpg",
    "category": [{ "$oid": "6908d50bce3345081ade433e" }],
    "unit": "Túi",
    "unitSize": 0.3,
    "stock": 16,
    "price": 49500,
    "discount": 5,
    "description": "Mô tả sản phẩm của hệ thông bán hàng.",
    "subcategory": [{ "$oid": "6908d541ce3345081ade434c" }]
  },
  {
    "_id": { "$oid": "6936d957fbb35077593b1245" },
    "name": "Cá ngừ ngâm dầu Tuna Việt Nam 140g giá tốt tại Bách hoá XANH",
    "sku": "ca-ngu-ngam-dau-tuna-viet-nam-lon-140g",
    "image": "https://cdnv2.tgdd.vn/bhx-static/bhx/Products/Images/3237/230040/bhx/ca-ngu-ngam-dau-tuna-viet-nam-lon-140g_202511201341292518.jpg",
    "category": [{ "$oid": "6936d53bfc65c6985f8c5770" }],
    "subcategory": [{ "$oid": "6936d555fc65c6985f8c5780" }],
    "unit": "Túi",
    "unitSize": 0.3,
    "stock": 14,
    "price": 25000,
    "discount": 5,
    "description": "Mô tả sản phẩm của hệ thông bán hàng."
  },
  {
    "_id": { "$oid": "6936d957fbb35077593b1246" },
    "name": "Combo 2 hộp trứng gà hộp 10 quả giá tốt tại Bách hoá XANH",
    "sku": "2-hop-trung-ga-hop-10-qua-giao-ngau-nhien-thuong-hieu",
    "image": "https://cdnv2.tgdd.vn/bhx-static/bhx/Products/Images/8783/358218/bhx/2-hop-trung-ga-hop-10-qua-giao-ngau-nhien-thuong-hieu_202510210955036207.jpg",
    "category": [{ "$oid": "6908d50bce3345081ade433e" }],
    "subcategory": [{ "$oid": "6908d575ce3345081ade4357" }],
    "unit": "Túi",
    "unitSize": 0.3,
    "stock": 9,
    "price": 64000,
    "discount": 5,
    "description": "Mô tả sản phẩm của hệ thông bán hàng."
  },
  {
    "_id": { "$oid": "6936d957fbb35077593b1247" },
    "name": "Bơ sáp 034 rất dẻo giá tốt tại Bách hoá XANH",
    "sku": "bo-sap-034-1kg",
    "image": "https://cdnv2.tgdd.vn/bhx-static/bhx/Products/Images/8788/223086/bhx/bo-sap-034-1kg_202504232346070859.jpg",
    "category": [{ "$oid": "6908d4e8ce3345081ade433b" }],
    "unit": "Túi",
    "unitSize": 0.3,
    "stock": 12,
    "price": 36400,
    "discount": 0,
    "description": "Mô tả sản phẩm của hệ thông bán hàng.",
    "subcategory": [{ "$oid": "6908d5b5ce3345081ade4362" }]
  },
  {
    "_id": { "$oid": "6936d957fbb35077593b1248" },
    "name": "Nho mẫu đơn nội địa Trung 500g tươi ngon, giá tốt",
    "sku": "nho-mau-don-noi-dia-trung-500g",
    "image": "https://cdnv2.tgdd.vn/bhx-static/bhx/Products/Images/8788/312875/bhx/nho-mau-don-noi-dia-trung-500g_202510271441422929.jpg",
    "category": [{ "$oid": "6908d4e8ce3345081ade433b" }],
    "unit": "Túi",
    "unitSize": 0.3,
    "stock": 20,
    "price": 49000,
    "discount": 0,
    "description": "Mô tả sản phẩm của hệ thông bán hàng.",
    "subcategory": [{ "$oid": "6908d5b5ce3345081ade4362" }]
  },
  {
    "_id": { "$oid": "6936d957fbb35077593b1249" },
    "name": "24 ly mì Hảo Hảo tôm chua cay 67g giá tốt tại Bách hoá XANH",
    "sku": "mi-ly-hao-hao-tom-chua-cay-67g-thung-24",
    "image": "https://www.bachhoaxanh.com/thung-24-ly-mi-handy-hao-hao-tom-chua-cay-67g-202306141327132226.jpg",
    "category": [{ "$oid": "6908d33cce3345081ade4321" }],
    "unit": "Túi",
    "unitSize": 0.3,
    "stock": 11,
    "price": 208000,
    "discount": 0,
    "description": "Mô tả sản phẩm của hệ thông bán hàng.",
    "subcategory": [{ "$oid": "6908d8bcce3345081ade43d3" }]
  },
  {
    "_id": { "$oid": "6936d957fbb35077593b124a" },
    "name": "Bí đỏ tròn dẻo, bùi ngon giá tốt tại Bách hoá XANH",
    "sku": "bi-do-tron-cat-san-1kg",
    "image": "https://cdnv2.tgdd.vn/bhx-static/bhx/Products/Images/8785/230438/bhx/bi-do-tron-cat-san-1kg_202504140844256340.jpg",
    "category": [{ "$oid": "6908d4e8ce3345081ade433b" }],
    "unit": "Túi",
    "unitSize": 0.3,
    "stock": 11,
    "price": 10500,
    "discount": 5,
    "description": "Mô tả sản phẩm của hệ thông bán hàng.",
    "subcategory": [{ "$oid": "6936d01e9bca55d5bca3016f" }]
  },
  {
    "_id": { "$oid": "6936d957fbb35077593b124b" },
    "name": "Ức gà phi lê có da tươi giá tốt tại Bách hoá XANH",
    "sku": "uc-ga-phi-le-co-da-tui-1kg",
    "image": "https://cdnv2.tgdd.vn/bhx-static/bhx/Products/Images/8790/222942/bhx/uc-ga-phi-le-co-da-tui-1kg_202504121718389083.jpg",
    "category": [{ "$oid": "6908d50bce3345081ade433e" }],
    "subcategory": [{ "$oid": "6911eb361141be8e94c27cf8" }],
    "unit": "Túi",
    "unitSize": 0.3,
    "stock": 3,
    "price": 30900,
    "discount": 0,
    "description": "Mô tả sản phẩm của hệ thông bán hàng."
  },
  {
    "_id": { "$oid": "6936d957fbb35077593b124c" },
    "name": "Bưởi da xanh tươi ngon giá tốt tại Bách hoá XANH",
    "sku": "buoi-da-xanh-loai-2-1kg",
    "image": "https://cdnv2.tgdd.vn/bhx-static/bhx/Products/Images/8788/223418/bhx/buoi-da-xanh-loai-2-1kg_202504122259394989.jpg",
    "category": [{ "$oid": "6908d4e8ce3345081ade433b" }],
    "unit": "Túi",
    "unitSize": 0.3,
    "stock": 6,
    "price": 62400,
    "discount": 0,
    "description": "Mô tả sản phẩm của hệ thông bán hàng.",
    "subcategory": [{ "$oid": "6908d5b5ce3345081ade4362" }]
  },
  {
    "_id": { "$oid": "6936d957fbb35077593b124d" },
    "name": "Hộp 10 trứng gà tươi giá tốt tại Bách hoá XANH",
    "sku": "hop-10-trung-ga-tuoi-tfood",
    "image": "https://cdnv2.tgdd.vn/bhx-static/bhx/Products/Images/8783/228775/bhx/hop-10-trung-ga-tuoi-tfood_202509301104427641.jpg",
    "category": [{ "$oid": "6908d50bce3345081ade433e" }],
    "subcategory": [{ "$oid": "6908d575ce3345081ade4357" }],
    "unit": "Túi",
    "unitSize": 0.3,
    "stock": 25,
    "price": 34000,
    "discount": 5,
    "description": "Mô tả sản phẩm của hệ thông bán hàng."
  },
  {
    "_id": { "$oid": "6936d957fbb35077593b124e" },
    "name": "Cá mòi xốt cà đậm đà 3 Cô Gái 155g giá tốt tại Bách hoá XANH",
    "sku": "ca-hop-ba-co-gai-nap-giut-155g",
    "image": "https://cdnv2.tgdd.vn/bhx-static/bhx/Products/Images/3237/77107/bhx/77107_202411121506253104.png",
    "category": [{ "$oid": "6936d53bfc65c6985f8c5770" }],
    "subcategory": [{ "$oid": "6936d555fc65c6985f8c5780" }],
    "unit": "Túi",
    "unitSize": 0.3,
    "stock": 27,
    "price": 19500,
    "discount": 0,
    "description": "Mô tả sản phẩm của hệ thông bán hàng."
  },
  {
    "_id": { "$oid": "6936d957fbb35077593b124f" },
    "name": "Dưa hấu đỏ tươi ngọt trái giá tốt tại Bách hoá XANH",
    "sku": "dua-hau-do-trai-25-27kg-1-trai",
    "image": "https://cdnv2.tgdd.vn/bhx-static/bhx/Products/Images/8788/339053/bhx/dua-hau-do-trai-25-kg-1-trai-clone_202505311641555096.jpg",
    "category": [{ "$oid": "6908d4e8ce3345081ade433b" }],
    "unit": "Túi",
    "unitSize": 0.3,
    "stock": 4,
    "price": 39900,
    "discount": 5,
    "description": "Mô tả sản phẩm của hệ thông bán hàng.",
    "subcategory": [{ "$oid": "6908d5b5ce3345081ade4362" }]
  },
  {
    "_id": { "$oid": "6936d957fbb35077593b1250" },
    "name": "Rau muống nước 400gr tươi ngon, giá tốt tại Bách hoá XANH",
    "sku": "rau-muong-nuoc-400gr",
    "image": "https://cdnv2.tgdd.vn/bhx-static/bhx/Products/Images/8820/335480/bhx/rau-muong-nuoc-400gr_202505081440372656.jpg",
    "category": [{ "$oid": "6908d4e8ce3345081ade433b" }],
    "unit": "Túi",
    "unitSize": 0.3,
    "stock": 3,
    "price": 16900,
    "discount": 10,
    "description": "Mô tả sản phẩm của hệ thông bán hàng.",
    "subcategory": [{ "$oid": "6908d5bece3345081ade4366" }]
  },
  {
    "_id": { "$oid": "6936d957fbb35077593b1251" },
    "name": "Ba rọi heo giá tốt tại Bách hoá XANH",
    "sku": "ba-roi-heo",
    "image": "https://cdnv2.tgdd.vn/bhx-static/bhx/Products/Images/8781/342025/bhx/ba-roi-heo_202510301701027235.jpg",
    "category": [{ "$oid": "6908d50bce3345081ade433e" }],
    "unit": "Túi",
    "unitSize": 0.3,
    "stock": 13,
    "price": 51000,
    "discount": 5,
    "description": "Mô tả sản phẩm của hệ thông bán hàng.",
    "subcategory": [{ "$oid": "6908d541ce3345081ade434c" }]
  },
  {
    "_id": { "$oid": "6936d957fbb35077593b1252" },
    "name": "Thịt má đùi gà cắt sẵn tại Bách hoá XANH",
    "sku": "ma-dui-ga-cat-san-tui-500g",
    "image": "https://cdnv2.tgdd.vn/bhx-static/bhx/Products/Images/8790/232930/bhx/ma-dui-ga-cat-san-tui-500g_202504121721171904.jpg",
    "category": [{ "$oid": "6908d50bce3345081ade433e" }],
    "subcategory": [{ "$oid": "6911eb361141be8e94c27cf8" }],
    "unit": "Túi",
    "unitSize": 0.3,
    "stock": 1,
    "price": 46000,
    "discount": 5,
    "description": "Mô tả sản phẩm của hệ thông bán hàng."
  },
  {
    "_id": { "$oid": "6936d957fbb35077593b1253" },
    "name": "Xoài keo giá tốt tại Bách hoá XANH",
    "sku": "xoai-keo-1kg",
    "image": "https://cdnv2.tgdd.vn/bhx-static/bhx/Products/Images/8788/233616/bhx/xoai-keo-1kg_202512031518390726.jpg",
    "category": [{ "$oid": "6908d4e8ce3345081ade433b" }],
    "unit": "Túi",
    "unitSize": 0.3,
    "stock": 10,
    "price": 19530,
    "discount": 10,
    "description": "Mô tả sản phẩm của hệ thông bán hàng.",
    "subcategory": [{ "$oid": "6908d5b5ce3345081ade4362" }]
  },
  {
    "_id": { "$oid": "6936d957fbb35077593b1255" },
    "name": "Cà rốt giá tốt tại Bách hoá XANH",
    "sku": "ca-rot-1kg",
    "image": "https://cdnv2.tgdd.vn/bhx-static/bhx/Products/Images/8785/234529/bhx/ca-rot-1kg_202504140920251335.jpg",
    "category": [{ "$oid": "6908d4e8ce3345081ade433b" }],
    "unit": "Túi",
    "unitSize": 0.3,
    "stock": 2,
    "price": 19000,
    "discount": 5,
    "description": "Mô tả sản phẩm của hệ thông bán hàng.",
    "subcategory": [{ "$oid": "6936d01e9bca55d5bca3016f" }]
  },
  {
    "_id": { "$oid": "6936d957fbb35077593b1256" },
    "name": "Rau dền khoảng 500g tươi ngon, giá tốt tại Bách hoá XANH",
    "sku": "rau-den-goi-500g",
    "image": "https://cdnv2.tgdd.vn/bhx-static/bhx/Products/Images/8820/271525/bhx/rau-den-goi-500g_202505061512562774.jpg",
    "category": [{ "$oid": "6908d4e8ce3345081ade433b" }],
    "unit": "Túi",
    "unitSize": 0.3,
    "stock": 26,
    "price": 16000,
    "discount": 5,
    "description": "Mô tả sản phẩm của hệ thông bán hàng.",
    "subcategory": [{ "$oid": "6908d5bece3345081ade4366" }]
  },
  {
    "_id": { "$oid": "6936d957fbb35077593b1257" },
    "name": "Mì mini Handy tôm chua cay 47g giá tốt tại Bách hoá XANH",
    "sku": "mi-an-lien-mini-handy-hao-hao-vi-tom-chua-cay-ly",
    "image": "https://www.bachhoaxanh.com/mi-an-lien-mini-handy-hao-hao-vi-tom-chua-cay-ly-47g-202306061434223246.jpg",
    "category": [{ "$oid": "6908d33cce3345081ade4321" }],
    "unit": "Túi",
    "unitSize": 0.3,
    "stock": 19,
    "price": 7500,
    "discount": 5,
    "description": "Mô tả sản phẩm của hệ thông bán hàng.",
    "subcategory": [{ "$oid": "6908d8bcce3345081ade43d3" }]
  },
  {
    "_id": { "$oid": "6936d957fbb35077593b1258" },
    "name": "Mì Jomo vị tôm chua cay gói 80g thơm ngon tại Bách hóa XANH",
    "sku": "mi-jomo-vi-tom-chua-cay-goi-80g",
    "image": "https://www.bachhoaxanh.com/mi-jomo-vi-tom-chua-cay-goi-80g-202306061451281147.jpg",
    "category": [{ "$oid": "6908d33cce3345081ade4321" }],
    "unit": "Túi",
    "unitSize": 0.3,
    "stock": 27,
    "price": 3900,
    "discount": 0,
    "description": "Mô tả sản phẩm của hệ thông bán hàng.",
    "subcategory": [{ "$oid": "6908d8bcce3345081ade43d3" }]
  },
  {
    "_id": { "$oid": "6936d957fbb35077593b1259" },
    "name": "Đùi bò 150g tươi ngon, giá tốt tại Bách hoá XANH",
    "sku": "dui-bo-150g",
    "image": "https://cdnv2.tgdd.vn/bhx-static/bhx/Products/Images/8139/341635/bhx/dui-bo-150g_202511041108475669.jpg",
    "category": [{ "$oid": "6908d50bce3345081ade433e" }],
    "unit": "Túi",
    "unitSize": 0.3,
    "stock": 27,
    "price": 42300,
    "discount": 5,
    "description": "Mô tả sản phẩm của hệ thông bán hàng.",
    "subcategory": [{ "$oid": "6911ed3f1141be8e94c27d4c" }]
  },
  {
    "_id": { "$oid": "6936d957fbb35077593b125a" },
    "name": "Mì Mama tôm sốt kem Tom Yum 55g giá tốt tại Bách hoá XANH",
    "sku": "mi-mama-sot-kem-tomyum-goi-55g-30",
    "image": "https://www.bachhoaxanh.com/mi-mama-huong-tom-sot-kem-tom-yum-goi-55g-202306061128531179.jpg",
    "category": [{ "$oid": "6908d33cce3345081ade4321" }],
    "unit": "Túi",
    "unitSize": 0.3,
    "stock": 12,
    "price": 8300,
    "discount": 0,
    "description": "Mô tả sản phẩm của hệ thông bán hàng.",
    "subcategory": [{ "$oid": "6908d8bcce3345081ade43d3" }]
  },
  {
    "_id": { "$oid": "6936d957fbb35077593b125b" },
    "name": "Gà mía nguyên con nhập khẩu giá tốt tại Bách hoá XANH",
    "sku": "ga-dai-nhap-khau-tui-500g",
    "image": "https://cdnv2.tgdd.vn/bhx-static/bhx/Products/Images/8790/239390/bhx/ga-dai-nhap-khau-tui-500g_202504231313088626.jpg",
    "category": [{ "$oid": "6908d50bce3345081ade433e" }],
    "subcategory": [{ "$oid": "6911eb361141be8e94c27cf8" }],
    "unit": "Túi",
    "unitSize": 0.3,
    "stock": 23,
    "price": 72000,
    "discount": 0,
    "description": "Mô tả sản phẩm của hệ thông bán hàng."
  },
  {
    "_id": { "$oid": "6936d957fbb35077593b125c" },
    "name": "Bắp mỹ giòn ngọt giá tốt tại Bách hoá XANH",
    "sku": "bap-my-1-trai",
    "image": "https://cdnv2.tgdd.vn/bhx-static/bhx/Products/Images/8785/241815/bhx/bap-my-1-trai_202504140933150847.jpg",
    "category": [{ "$oid": "6908d4e8ce3345081ade433b" }],
    "unit": "Túi",
    "unitSize": 0.3,
    "stock": 18,
    "price": 10000,
    "discount": 5,
    "description": "Mô tả sản phẩm của hệ thông bán hàng.",
    "subcategory": [{ "$oid": "6936d01e9bca55d5bca3016f" }]
  },
  {
    "_id": { "$oid": "6936d957fbb35077593b125d" },
    "name": "Xương que nhập khẩu đông lạnh 500g giá tốt tại Bách hoá XANH",
    "sku": "xuong-que-heo-nhap-khau-dong-lanh-tui-500g",
    "image": "https://cdnv2.tgdd.vn/bhx-static/bhx/Products/Images/8781/249017/bhx/xuong-que-heo-nhap-khau-dong-lanh-tui-500g_202511031521551395.jpg",
    "category": [{ "$oid": "6908d50bce3345081ade433e" }],
    "unit": "Túi",
    "unitSize": 0.3,
    "stock": 13,
    "price": 29900,
    "discount": 5,
    "description": "Mô tả sản phẩm của hệ thông bán hàng.",
    "subcategory": [{ "$oid": "6908d541ce3345081ade434c" }]
  },
  {
    "_id": { "$oid": "6936d957fbb35077593b125e" },
    "name": "Trứng gà so hộp 10 tặng 2 chất lượng tại Bách hoá XANH",
    "sku": "trung-ga-so-hop-10-tang-2",
    "image": "https://cdnv2.tgdd.vn/bhx-static/bhx/Products/Images/8783/309143/bhx/trung-ga-so-hop-10-tang-2_202509301125211985.jpg",
    "category": [{ "$oid": "6908d50bce3345081ade433e" }],
    "subcategory": [{ "$oid": "6908d575ce3345081ade4357" }],
    "unit": "Túi",
    "unitSize": 0.3,
    "stock": 2,
    "price": 34000,
    "discount": 0,
    "description": "Mô tả sản phẩm của hệ thông bán hàng."
  },
  {
    "_id": { "$oid": "6936d957fbb35077593b125f" },
    "name": "Thịt đùi heo 300g giá tốt tại Bách hoá XANH",
    "sku": "thit-dui-heo-300g",
    "image": "https://cdnv2.tgdd.vn/bhx-static/bhx/Products/Images/8781/332800/bhx/thit-dui-heo-300g_202512021317567059.jpg",
    "category": [{ "$oid": "6908d50bce3345081ade433e" }],
    "unit": "Túi",
    "unitSize": 0.3,
    "stock": 7,
    "price": 29700,
    "discount": 5,
    "description": "Mô tả sản phẩm của hệ thông bán hàng.",
    "subcategory": [{ "$oid": "6908d541ce3345081ade434c" }]
  },
  {
    "_id": { "$oid": "6936d957fbb35077593b1260" },
    "name": "Cam sành tươi ngon, mọng nước tại Bách hoá XANH",
    "sku": "cam-sanh",
    "image": "https://cdnv2.tgdd.vn/bhx-static/bhx/Products/Images/8788/321604/bhx/cam-sanh_202510221511128369.jpg",
    "category": [{ "$oid": "6908d4e8ce3345081ade433b" }],
    "unit": "Túi",
    "unitSize": 0.3,
    "stock": 12,
    "price": 7500,
    "discount": 5,
    "description": "Mô tả sản phẩm của hệ thông bán hàng.",
    "subcategory": [{ "$oid": "6908d5b5ce3345081ade4362" }]
  },
  {
    "_id": { "$oid": "6936d957fbb35077593b1261" },
    "name": "2 hộp trứng cút hộp 30 quả giá tốt tại Bách hoá XANH",
    "sku": "2-hop-trung-cut-hop-30-qua-tu-300g-360g-giao-ngau-nhien-thuong-hieu",
    "image": "https://cdnv2.tgdd.vn/bhx-static/bhx/Products/Images/8783/358504/bhx/trung-cut-hop-30-qua-tu-300g-360g-giao-ngau-nhien-thuong-hieu-clone_202510301458324264.jpg",
    "category": [{ "$oid": "6908d50bce3345081ade433e" }],
    "subcategory": [{ "$oid": "6908d575ce3345081ade4357" }],
    "unit": "Túi",
    "unitSize": 0.3,
    "stock": 14,
    "price": 45000,
    "discount": 0,
    "description": "Mô tả sản phẩm của hệ thông bán hàng."
  },
  {
    "_id": { "$oid": "6936d957fbb35077593b1262" },
    "name": "Bơ Booth giá tốt tại Bách hoá XANH",
    "sku": "bo-booth-1kg",
    "image": "https://cdnv2.tgdd.vn/bhx-static/bhx/Products/Images/8788/234066/bhx/bo-booth-1kg_202504231026259925.jpg",
    "category": [{ "$oid": "6908d4e8ce3345081ade433b" }],
    "unit": "Túi",
    "unitSize": 0.3,
    "stock": 10,
    "price": 16200,
    "discount": 10,
    "description": "Mô tả sản phẩm của hệ thông bán hàng.",
    "subcategory": [{ "$oid": "6908d5b5ce3345081ade4362" }]
  },
  {
    "_id": { "$oid": "6936d957fbb35077593b1263" },
    "name": "Thùng 30 gói mì Omachi lẩu tôm càng 80g tại Bách hóa XANH",
    "sku": "thung-30-goi-mi-khoai-tay-omachi-tom-chua-cay-thai-80g",
    "image": "https://cdnv2.tgdd.vn/bhx-static/bhx/Products/Images/2565/289585/bhx/thung-30-goi-mi-khoai-tay-omachi-tom-chua-cay-thai-80g_202506211856200697.jpg",
    "category": [{ "$oid": "6908d33cce3345081ade4321" }],
    "unit": "Túi",
    "unitSize": 0.3,
    "stock": 3,
    "price": 246000,
    "discount": 0,
    "description": "Mô tả sản phẩm của hệ thông bán hàng.",
    "subcategory": [{ "$oid": "6908d8bcce3345081ade43d3" }]
  },
  {
    "_id": { "$oid": "6936d957fbb35077593b1264" },
    "name": "Đầu cá hồi salar làm sạch giá tốt tại Bách hoá XANH",
    "sku": "dau-ca-hoi-tuoi-khay-1kg-300g-500g-cai",
    "image": "https://cdnv2.tgdd.vn/bhx-static/bhx/Products/Images/8782/274988/bhx/dau-ca-hoi-tuoi-khay-1kg-300g-500g-cai_202506271409568361.jpg",
    "category": [{ "$oid": "6908d50bce3345081ade433e" }],
    "unit": "Túi",
    "unitSize": 0.3,
    "stock": 20,
    "price": 69000,
    "discount": 5,
    "description": "Mô tả sản phẩm của hệ thông bán hàng.",
    "subcategory": [{ "$oid": "6911ef161141be8e94c27e05" }]
  },
  {
    "_id": { "$oid": "6936d957fbb35077593b1265" },
    "name": "Cải bẹ xanh 300g tươi ngon, giá cả cực tốt | Bách hoá XANH",
    "sku": "cai-be-xanh-goi-400g",
    "image": "https://cdnv2.tgdd.vn/bhx-static/bhx/Products/Images/8820/335481/bhx/cai-be-xanh-goi-400g_202506020910432774.jpg",
    "category": [{ "$oid": "6908d4e8ce3345081ade433b" }],
    "unit": "Túi",
    "unitSize": 0.3,
    "stock": 13,
    "price": 16900,
    "discount": 0,
    "description": "Mô tả sản phẩm của hệ thông bán hàng.",
    "subcategory": [{ "$oid": "6908d5bece3345081ade4366" }]
  },
  {
    "_id": { "$oid": "6936d957fbb35077593b1266" },
    "name": "Cá ngừ xốt cà Tuna Việt Nam 140g giá tốt tại Bách hoá XANH",
    "sku": "ca-ngu-xot-ca-chua-tuna-viet-nam-lon-140g",
    "image": "https://cdnv2.tgdd.vn/bhx-static/bhx/Products/Images/3237/230043/bhx/230043_202411121545535387.png",
    "category": [{ "$oid": "6936d53bfc65c6985f8c5770" }],
    "subcategory": [{ "$oid": "6936d555fc65c6985f8c5780" }],
    "unit": "Túi",
    "unitSize": 0.3,
    "stock": 27,
    "price": 12500,
    "discount": 5,
    "description": "Mô tả sản phẩm của hệ thông bán hàng."
  },
  {
    "_id": { "$oid": "6936d957fbb35077593b1267" },
    "name": "Má đùi gà tươi sạch C.P khay 500g giá tốt tại Bách hoá XANH",
    "sku": "ma-dui-ga-vi-500g",
    "image": "https://cdnv2.tgdd.vn/bhx-static/bhx/Products/Images/8790/226883/bhx/ma-dui-ga-vi-500g_202511041054516000.jpg",
    "category": [{ "$oid": "6908d50bce3345081ade433e" }],
    "subcategory": [{ "$oid": "6911eb361141be8e94c27cf8" }],
    "unit": "Túi",
    "unitSize": 0.3,
    "stock": 30,
    "price": 38930,
    "discount": 10,
    "description": "Mô tả sản phẩm của hệ thông bán hàng."
  },
  {
    "_id": { "$oid": "6936d957fbb35077593b1268" },
    "name": "Lê đường tươi ngon, giá tốt tại Bách hoá XANH",
    "sku": "le-duong-noi-dia-trung-tui-3-trai",
    "image": "https://cdnv2.tgdd.vn/bhx-static/bhx/Products/Images/8788/339886/bhx/le-duong-noi-dia-trung-tui-3-trai_202506270932155019.jpg",
    "category": [{ "$oid": "6908d4e8ce3345081ade433b" }],
    "unit": "Túi",
    "unitSize": 0.3,
    "stock": 20,
    "price": 58900,
    "discount": 10,
    "description": "Mô tả sản phẩm của hệ thông bán hàng.",
    "subcategory": [{ "$oid": "6908d5b5ce3345081ade4362" }]
  },
  {
    "_id": { "$oid": "6936d957fbb35077593b1269" },
    "name": "Quýt mini tươi ngon, giá tốt tại Bách hoá XANH",
    "sku": "quyt-mini-tui-500g",
    "image": "https://cdnv2.tgdd.vn/bhx-static/bhx/Products/Images/8788/223036/bhx/quyt-mini-tui-500g_202504231122461363.jpg",
    "category": [{ "$oid": "6908d4e8ce3345081ade433b" }],
    "unit": "Túi",
    "unitSize": 0.3,
    "stock": 26,
    "price": 39000,
    "discount": 0,
    "description": "Mô tả sản phẩm của hệ thông bán hàng.",
    "subcategory": [{ "$oid": "6908d5b5ce3345081ade4362" }]
  },
  {
    "_id": { "$oid": "6936d957fbb35077593b126a" },
    "name": "30 gói Hảo Hảo tôm chua cay 75g giá tốt tại Bách hoá XANH",
    "sku": "mi-hao-hao-tom-chua-cay-75g-30",
    "image": "https://cdnv2.tgdd.vn/bhx-static/bhx/Products/Images/2565/85959/bhx/85959_202410151353322317.jpg",
    "category": [{ "$oid": "6908d33cce3345081ade4321" }],
    "unit": "Túi",
    "unitSize": 0.3,
    "stock": 4,
    "price": 116000,
    "discount": 10,
    "description": "Mô tả sản phẩm của hệ thông bán hàng.",
    "subcategory": [{ "$oid": "6908d8bcce3345081ade43d3" }]
  },
  {
    "_id": { "$oid": "6936d957fbb35077593b126b" },
    "name": "Đùi tỏi gà tươi túi 500g (2-4 đùi) giá tốt tại Bách hoá XANH",
    "sku": "dui-toi-ga-tui-500g",
    "image": "https://cdnv2.tgdd.vn/bhx-static/bhx/Products/Images/8790/226882/bhx/dui-toi-ga-tui-500g_202504121620514675.jpg",
    "category": [{ "$oid": "6908d50bce3345081ade433e" }],
    "subcategory": [{ "$oid": "6911eb361141be8e94c27cf8" }],
    "unit": "Túi",
    "unitSize": 0.3,
    "stock": 21,
    "price": 61000,
    "discount": 10,
    "description": "Mô tả sản phẩm của hệ thông bán hàng."
  },
  {
    "_id": { "$oid": "6936d957fbb35077593b126c" },
    "name": "Chân giò heo nhập khẩu giá tốt tại Bách hoá XANH",
    "sku": "chan-gio-heo-nhap-khau-1kg",
    "image": "https://cdnv2.tgdd.vn/bhx-static/bhx/Products/Images/8781/233758/bhx/chan-gio-heo-nhap-khau-1kg_202511031508014310.jpg",
    "category": [{ "$oid": "6908d50bce3345081ade433e" }],
    "unit": "Túi",
    "unitSize": 0.3,
    "stock": 20,
    "price": 29400,
    "discount": 0,
    "description": "Mô tả sản phẩm của hệ thông bán hàng.",
    "subcategory": [{ "$oid": "6908d541ce3345081ade434c" }]
  },
  {
    "_id": { "$oid": "6936d957fbb35077593b126d" },
    "name": "Cam sành tươi ngon, mọng nước tại Bách hoá XANH",
    "sku": "cam-sanh-5kg-trai-tu-130g-tro-len",
    "image": "https://cdnv2.tgdd.vn/bhx-static/bhx/Products/Images/8788/358219/bhx/cam-sanh-5kg-trai-tu-130g-tro-len_202510211011044800.jpg",
    "category": [{ "$oid": "6908d4e8ce3345081ade433b" }],
    "unit": "Túi",
    "unitSize": 0.3,
    "stock": 19,
    "price": 53000,
    "discount": 0,
    "description": "Mô tả sản phẩm của hệ thông bán hàng.",
    "subcategory": [{ "$oid": "6908d5b5ce3345081ade4362" }]
  },
  {
    "_id": { "$oid": "6936d957fbb35077593b126e" },
    "name": "Đùi gà góc tư làm sạch túi 500g giá tốt tại Bách hoá XANH",
    "sku": "dui-ga-goc-tu-tui-500g",
    "image": "https://cdnv2.tgdd.vn/bhx-static/bhx/Products/Images/8790/226949/bhx/dui-ga-goc-tu-tui-500g_202510231104002862.jpg",
    "category": [{ "$oid": "6908d50bce3345081ade433e" }],
    "subcategory": [{ "$oid": "6911eb361141be8e94c27cf8" }],
    "unit": "Túi",
    "unitSize": 0.3,
    "stock": 1,
    "price": 48000,
    "discount": 5,
    "description": "Mô tả sản phẩm của hệ thông bán hàng."
  },
  {
    "_id": { "$oid": "6936d957fbb35077593b126f" },
    "name": "Ổi Đài Loan túi 1kg (3-5 trái) giá tốt tại Bách hoá XANH",
    "sku": "oi-dai-loan-tui-1kg",
    "image": "https://cdnv2.tgdd.vn/bhx-static/bhx/Products/Images/8788/226921/bhx/oi-dai-loan-tui-1kg_202511031551328365.jpg",
    "category": [{ "$oid": "6908d4e8ce3345081ade433b" }],
    "unit": "Túi",
    "unitSize": 0.3,
    "stock": 29,
    "price": 13500,
    "discount": 5,
    "description": "Mô tả sản phẩm của hệ thông bán hàng.",
    "subcategory": [{ "$oid": "6908d5b5ce3345081ade4362" }]
  },
  {
    "_id": { "$oid": "6936d957fbb35077593b1270" },
    "name": "Chuối già Nam Mỹ giàu dinh dưỡng, tiện lợi tại Bách hoá XANH",
    "sku": "chuoi-gia-giong-nam-my",
    "image": "https://cdnv2.tgdd.vn/bhx-static/bhx/Products/Images/8788/228923/bhx/chuoi-gia-giong-nam-my_202512031458490151.jpg",
    "category": [{ "$oid": "6908d4e8ce3345081ade433b" }],
    "unit": "Túi",
    "unitSize": 0.3,
    "stock": 22,
    "price": 16000,
    "discount": 0,
    "description": "Mô tả sản phẩm của hệ thông bán hàng.",
    "subcategory": [{ "$oid": "6908d5b5ce3345081ade4362" }]
  },
  {
    "_id": { "$oid": "6936d957fbb35077593b1271" },
    "name": "Cải bó xôi túi 300gr tươi ngon, giá cả tốt tại Bách hoá XANH",
    "sku": "cai-bo-xoi-tui-300gr",
    "image": "https://cdnv2.tgdd.vn/bhx-static/bhx/Products/Images/8820/275306/bhx/cai-bo-xoi-tui-300gr_202505100838502944.jpg",
    "category": [{ "$oid": "6908d4e8ce3345081ade433b" }],
    "unit": "Túi",
    "unitSize": 0.3,
    "stock": 30,
    "price": 29000,
    "discount": 10,
    "description": "Mô tả sản phẩm của hệ thông bán hàng.",
    "subcategory": [{ "$oid": "6908d5bece3345081ade4366" }]
  },
  {
    "_id": { "$oid": "6936d957fbb35077593b1272" },
    "name": "Canh khoai mỡ tôm khay 400g tại Bách hoá XANH",
    "sku": "canh-khoai-mo-tom-khay-400g",
    "image": "https://cdnv2.tgdd.vn/bhx-static/bhx/Products/Images/12718/337069/bhx/canh-khoai-mo-tom-khay-400g_202508181021546796.jpg",
    "category": [{ "$oid": "6908d4e8ce3345081ade433b" }],
    "unit": "Túi",
    "unitSize": 0.3,
    "stock": 5,
    "price": 45000,
    "discount": 0,
    "description": "Mô tả sản phẩm của hệ thông bán hàng.",
    "subcategory": [{ "$oid": "6936d01e9bca55d5bca3016f" }]
  },
  {
    "_id": { "$oid": "6936d957fbb35077593b1273" },
    "name": "Quýt mini ngọt giá tốt tại Bách hoá XANH",
    "sku": "quyt-mini-nhap-khau-trung-quoc-hop-1kg-khoang-20-trai",
    "image": "https://cdnv2.tgdd.vn/bhx-static/bhx/Products/Images/8788/231363/bhx/quyt-mini-nhap-khau-trung-quoc-hop-1kg-khoang-20-trai_202510280936028642.jpg",
    "category": [{ "$oid": "6908d4e8ce3345081ade433b" }],
    "unit": "Túi",
    "unitSize": 0.3,
    "stock": 22,
    "price": 22500,
    "discount": 10,
    "description": "Mô tả sản phẩm của hệ thông bán hàng.",
    "subcategory": [{ "$oid": "6908d5b5ce3345081ade4362" }]
  },
  {
    "_id": { "$oid": "6936d957fbb35077593b1274" },
    "name": "Thanh long ruột đỏ giá tốt tại Bách hoá XANH",
    "sku": "thanh-long-ruot-do-1kg",
    "image": "https://cdnv2.tgdd.vn/bhx-static/bhx/Products/Images/8788/234065/bhx/thanh-long-ruot-do-1kg_202510211435522470.jpg",
    "category": [{ "$oid": "6908d4e8ce3345081ade433b" }],
    "unit": "Túi",
    "unitSize": 0.3,
    "stock": 23,
    "price": 28000,
    "discount": 5,
    "description": "Mô tả sản phẩm của hệ thông bán hàng.",
    "subcategory": [{ "$oid": "6908d5b5ce3345081ade4362" }]
  },
  {
    "_id": { "$oid": "6936d957fbb35077593b1275" },
    "name": "Thịt heo xay CP khay 200g chất lượng tại Bách hoá XANH",
    "sku": "thit-heo-xay-cp-khay-200g",
    "image": "https://cdnv2.tgdd.vn/bhx-static/bhx/Products/Images/8781/283165/bhx/thit-heo-xay-cp-khay-200g_202511041615328979.jpg",
    "category": [{ "$oid": "6908d50bce3345081ade433e" }],
    "unit": "Túi",
    "unitSize": 0.3,
    "stock": 10,
    "price": 25000,
    "discount": 10,
    "description": "Mô tả sản phẩm của hệ thông bán hàng.",
    "subcategory": [{ "$oid": "6908d541ce3345081ade434c" }]
  },
  {
    "_id": { "$oid": "6936d957fbb35077593b1276" },
    "name": "Su su giá tốt tại Bách hoá XANH",
    "sku": "su-su-500g",
    "image": "https://cdnv2.tgdd.vn/bhx-static/bhx/Products/Images/8785/230462/bhx/su-su-500g_202507031125252608.jpg",
    "category": [{ "$oid": "6908d4e8ce3345081ade433b" }],
    "unit": "Túi",
    "unitSize": 0.3,
    "stock": 11,
    "price": 17500,
    "discount": 10,
    "description": "Mô tả sản phẩm của hệ thông bán hàng.",
    "subcategory": [{ "$oid": "6936d01e9bca55d5bca3016f" }]
  },
  {
    "_id": { "$oid": "6936d957fbb35077593b1277" },
    "name": "Dưa hấu không hạt ngọt trái giá tốt tại Bách hoá XANH",
    "sku": "dua-hau-khong-hat-1kg",
    "image": "https://cdnv2.tgdd.vn/bhx-static/bhx/Products/Images/8788/226966/bhx/dua-hau-khong-hat-1kg_202504121601454174.jpg",
    "category": [{ "$oid": "6908d4e8ce3345081ade433b" }],
    "unit": "Túi",
    "unitSize": 0.3,
    "stock": 22,
    "price": 44600,
    "discount": 10,
    "description": "Mô tả sản phẩm của hệ thông bán hàng.",
    "subcategory": [{ "$oid": "6908d5b5ce3345081ade4362" }]
  },
  {
    "_id": { "$oid": "6936d957fbb35077593b1278" },
    "name": "Trứng vịt hộp 10 quả chất lượng tại Bách hoá XANH",
    "sku": "trung-vit-hop-10-qua",
    "image": "https://cdnv2.tgdd.vn/bhx-static/bhx/Products/Images/8783/311102/bhx/trung-vit-hop-10-qua_202509301122002833.jpg",
    "category": [{ "$oid": "6908d50bce3345081ade433e" }],
    "subcategory": [{ "$oid": "6908d575ce3345081ade4357" }],
    "unit": "Túi",
    "unitSize": 0.3,
    "stock": 15,
    "price": 38000,
    "discount": 10,
    "description": "Mô tả sản phẩm của hệ thông bán hàng."
  },
  {
    "_id": { "$oid": "6936d957fbb35077593b1279" },
    "name": "Rau muống hạt 300g giá tốt tại Bách hoá XANH",
    "sku": "rau-muong-hat-baby-goi-300g",
    "image": "https://cdnv2.tgdd.vn/bhx-static/bhx/Products/Images/8820/223334/bhx/rau-muong-hat-baby-goi-300g_202505261048323712.jpg",
    "category": [{ "$oid": "6908d4e8ce3345081ade433b" }],
    "unit": "Túi",
    "unitSize": 0.3,
    "stock": 17,
    "price": 16900,
    "discount": 5,
    "description": "Mô tả sản phẩm của hệ thông bán hàng.",
    "subcategory": [{ "$oid": "6908d5bece3345081ade4366" }]
  },
  {
    "_id": { "$oid": "6936d957fbb35077593b127b" },
    "name": "Mì ăn liền Kang Shi Fu vị bò hầm hộp 110g Bách hóa XANH",
    "sku": "mi-an-lien-kang-shi-fu-vi-bo-ham-hop-110g",
    "image": "https://www.bachhoaxanh.com/mi-an-lien-kang-shi-fu-vi-bo-ham-hop-110g-202205161528237739.jpg",
    "category": [{ "$oid": "6908d33cce3345081ade4321" }],
    "unit": "Túi",
    "unitSize": 0.3,
    "stock": 29,
    "price": null,
    "discount": 10,
    "description": "Mô tả sản phẩm của hệ thông bán hàng.",
    "subcategory": [{ "$oid": "6908d8bcce3345081ade43d3" }]
  },
  {
    "_id": { "$oid": "6936d957fbb35077593b127c" },
    "name": "Rau lang 300g tươi ngon, giá cả cực tốt tại Bách hoá XANH",
    "sku": "rau-lang-300g",
    "image": "https://cdnv2.tgdd.vn/bhx-static/bhx/Products/Images/8820/336819/bhx/rau-lang-300g_202505271413457625.jpg",
    "category": [{ "$oid": "6908d4e8ce3345081ade433b" }],
    "unit": "Túi",
    "unitSize": 0.3,
    "stock": 7,
    "price": 16900,
    "discount": 5,
    "description": "Mô tả sản phẩm của hệ thông bán hàng.",
    "subcategory": [{ "$oid": "6908d5bece3345081ade4366" }]
  },
  {
    "_id": { "$oid": "6936d957fbb35077593b127d" },
    "name": "Mì Mama hương tôm Tom Yum gói 55g giá tốt tại Bách hoá XANH",
    "sku": "mi-tom-tomyum-55-gr",
    "image": "https://www.bachhoaxanh.com/mi-mama-huong-tom-tom-yum-goi-55g-202306061124018045.jpg",
    "category": [{ "$oid": "6908d33cce3345081ade4321" }],
    "unit": "Túi",
    "unitSize": 0.3,
    "stock": 1,
    "price": 8300,
    "discount": 10,
    "description": "Mô tả sản phẩm của hệ thông bán hàng.",
    "subcategory": [{ "$oid": "6908d8bcce3345081ade43d3" }]
  },
  {
    "_id": { "$oid": "6936d957fbb35077593b127e" },
    "name": "Cánh giữa gà 300g giá tốt tại Bách hoá XANH",
    "sku": "canh-giua-ga-300g",
    "image": "https://cdnv2.tgdd.vn/bhx-static/bhx/Products/Images/8790/332896/bhx/canh-giua-ga-300g_202508131613153707.jpg",
    "category": [{ "$oid": "6908d50bce3345081ade433e" }],
    "subcategory": [{ "$oid": "6911eb361141be8e94c27cf8" }],
    "unit": "Túi",
    "unitSize": 0.3,
    "stock": 27,
    "price": 49500,
    "discount": 5,
    "description": "Mô tả sản phẩm của hệ thông bán hàng."
  },
  {
    "_id": { "$oid": "6936d957fbb35077593b1280" },
    "name": "Xương gà có thịt 500g giá tốt tại Bách hoá XANH",
    "sku": "xuong-ga-tui-500g",
    "image": "https://cdnv2.tgdd.vn/bhx-static/bhx/Products/Images/8790/232937/bhx/xuong-ga-tui-500g_202504150904550535.jpg",
    "category": [{ "$oid": "6908d50bce3345081ade433e" }],
    "subcategory": [{ "$oid": "6911eb361141be8e94c27cf8" }],
    "unit": "Túi",
    "unitSize": 0.3,
    "stock": 9,
    "price": 14200,
    "discount": 5,
    "description": "Mô tả sản phẩm của hệ thông bán hàng."
  },
  {
    "_id": { "$oid": "6936d957fbb35077593b1281" },
    "name": "Thùng 30 gói mì Gấu Đỏ tôm gà 63g giá tốt tại Bách hoá XANH",
    "sku": "mi-gau-do-tom-ga-hanh-phi-64g-30-thung",
    "image": "https://www.bachhoaxanh.com/thung-30-goi-mi-gau-do-tom-va-ga-63g-202407121435290079.jpg",
    "category": [{ "$oid": "6908d33cce3345081ade4321" }],
    "unit": "Túi",
    "unitSize": 0.3,
    "stock": 14,
    "price": 86000,
    "discount": 0,
    "description": "Mô tả sản phẩm của hệ thông bán hàng.",
    "subcategory": [{ "$oid": "6908d8bcce3345081ade43d3" }]
  },
  {
    "_id": { "$oid": "6936d957fbb35077593b1282" },
    "name": "Thịt ức gà phi lê có da túi 500g giá tốt tại Bách hoá XANH",
    "sku": "uc-ga-phi-le-co-da-tui-500g",
    "image": "https://cdnv2.tgdd.vn/bhx-static/bhx/Products/Images/8790/234105/bhx/uc-ga-phi-le-co-da-tui-500g_202504121710454323.jpg",
    "category": [{ "$oid": "6908d50bce3345081ade433e" }],
    "subcategory": [{ "$oid": "6911eb361141be8e94c27cf8" }],
    "unit": "Túi",
    "unitSize": 0.3,
    "stock": 5,
    "price": 51500,
    "discount": 5,
    "description": "Mô tả sản phẩm của hệ thông bán hàng."
  },
  {
    "_id": { "$oid": "6936d957fbb35077593b1283" },
    "name": "Bắp cải trắng giá tốt tại Bách hoá XANH",
    "sku": "bap-cai-trang-tui-1kg",
    "image": "https://cdnv2.tgdd.vn/bhx-static/bhx/Products/Images/8785/234101/bhx/bap-cai-trang-tui-1kg_202505211032411439.jpg",
    "category": [{ "$oid": "6908d4e8ce3345081ade433b" }],
    "unit": "Túi",
    "unitSize": 0.3,
    "stock": 15,
    "price": 26400,
    "discount": 10,
    "description": "Mô tả sản phẩm của hệ thông bán hàng.",
    "subcategory": [{ "$oid": "6936d01e9bca55d5bca3016f" }]
  },
  {
    "_id": { "$oid": "6936d957fbb35077593b1284" },
    "name": "Cá kho thịt 3 Bông mai Vissan 150g giá tốt tại Bách hoá XANH",
    "sku": "ca-kho-thit-vissan-150g",
    "image": "https://www.bachhoaxanh.com/ca-kho-thit-3-bong-mai-vissan-hop-150g-202205191340222544.jpg",
    "category": [{ "$oid": "6936d53bfc65c6985f8c5770" }],
    "subcategory": [{ "$oid": "6936d555fc65c6985f8c5780" }],
    "unit": "Túi",
    "unitSize": 0.3,
    "stock": 25,
    "price": null,
    "discount": 0,
    "description": "Mô tả sản phẩm của hệ thông bán hàng."
  },
  {
    "_id": { "$oid": "6936d957fbb35077593b1285" },
    "name": "Cá lóc làm sạch 500g giá rẻ tại Bách hoá XANH",
    "sku": "ca-loc-song-tui-500g",
    "image": "https://cdnv2.tgdd.vn/bhx-static/bhx/Products/Images/8782/222961/bhx/ca-loc-song-tui-500g_202505252004048182.jpg",
    "category": [{ "$oid": "6908d50bce3345081ade433e" }],
    "unit": "Túi",
    "unitSize": 0.3,
    "stock": 2,
    "price": 50500,
    "discount": 0,
    "description": "Mô tả sản phẩm của hệ thông bán hàng.",
    "subcategory": [{ "$oid": "6911ef161141be8e94c27e05" }]
  },
  {
    "_id": { "$oid": "6936d957fbb35077593b1286" },
    "name": "Táo Gala mini túi 8 trái tươi ngon giá tốt tại Bách hoá XANH",
    "sku": "tao-gala-mini-tui-8-trai",
    "image": "https://cdnv2.tgdd.vn/bhx-static/bhx/Products/Images/8788/337376/bhx/tao-gala-mini-tui-8-trai_202510291405115328.jpg",
    "category": [{ "$oid": "6908d4e8ce3345081ade433b" }],
    "unit": "Túi",
    "unitSize": 0.3,
    "stock": 13,
    "price": 42000,
    "discount": 10,
    "description": "Mô tả sản phẩm của hệ thông bán hàng.",
    "subcategory": [{ "$oid": "6908d5b5ce3345081ade4362" }]
  },
  {
    "_id": { "$oid": "6936d957fbb35077593b1287" },
    "name": "Rau cải ngồng tươi bịch 300g giá tốt tại Bách hoá XANH",
    "sku": "cai-ngong-tui-300g",
    "image": "https://cdnv2.tgdd.vn/bhx-static/bhx/Products/Images/8820/222865/bhx/cai-ngong-tui-300g_202506021525116652.jpg",
    "category": [{ "$oid": "6908d4e8ce3345081ade433b" }],
    "unit": "Túi",
    "unitSize": 0.3,
    "stock": 17,
    "price": 16900,
    "discount": 5,
    "description": "Mô tả sản phẩm của hệ thông bán hàng.",
    "subcategory": [{ "$oid": "6908d5bece3345081ade4366" }]
  },
  {
    "_id": { "$oid": "6936d957fbb35077593b1288" },
    "name": "Cá basa cắt khúc giá rẻ tại Bách hoá XANH",
    "sku": "ca-basa-cat-khuc",
    "image": "https://cdnv2.tgdd.vn/bhx-static/bhx/Products/Images/8782/308046/bhx/ca-basa-cat-khuc_202511251706118061.jpg",
    "category": [{ "$oid": "6908d50bce3345081ade433e" }],
    "unit": "Túi",
    "unitSize": 0.3,
    "stock": 11,
    "price": 29400,
    "discount": 0,
    "description": "Mô tả sản phẩm của hệ thông bán hàng.",
    "subcategory": [{ "$oid": "6911ef161141be8e94c27e05" }]
  },
  {
    "_id": { "$oid": "6936d957fbb35077593b1289" },
    "name": "Cánh gà giá tốt tại Bách hoá XANH",
    "sku": "canh-ga-1kg",
    "image": "https://cdnv2.tgdd.vn/bhx-static/bhx/Products/Images/8790/226874/bhx/canh-ga-1kg_202504121623514676.jpg",
    "category": [{ "$oid": "6908d50bce3345081ade433e" }],
    "subcategory": [{ "$oid": "6911eb361141be8e94c27cf8" }],
    "unit": "Túi",
    "unitSize": 0.3,
    "stock": 26,
    "price": 29700,
    "discount": 10,
    "description": "Mô tả sản phẩm của hệ thông bán hàng."
  },
  {
    "_id": { "$oid": "6936d957fbb35077593b128a" },
    "name": "Thùng 30 gói mì 3 Miền Gold cay 3 cấp độ 75g | Bách hóa XANH",
    "sku": "thung-30-goi-mi-3-mien-gold-cay-3-cap-do-goi-75g",
    "image": "https://www.bachhoaxanh.com/mi-3-mien-cay-3-cap-do-goi-75g-clone-202406131513193880.jpg",
    "category": [{ "$oid": "6908d33cce3345081ade4321" }],
    "unit": "Túi",
    "unitSize": 0.3,
    "stock": 24,
    "price": 125000,
    "discount": 5,
    "description": "Mô tả sản phẩm của hệ thông bán hàng.",
    "subcategory": [{ "$oid": "6908d8bcce3345081ade43d3" }]
  },
  {
    "_id": { "$oid": "6936d957fbb35077593b128b" },
    "name": "Lê đường Trung Quốc 1kg (3 - 5 trái) giá tốt",
    "sku": "le-duong-hop-1kg",
    "image": "https://cdnv2.tgdd.vn/bhx-static/bhx/Products/Images/8788/223091/bhx/le-duong-hop-1kg_202504121512329487.jpg",
    "category": [{ "$oid": "6908d4e8ce3345081ade433b" }],
    "unit": "Túi",
    "unitSize": 0.3,
    "stock": 29,
    "price": 39000,
    "discount": 5,
    "description": "Mô tả sản phẩm của hệ thông bán hàng.",
    "subcategory": [{ "$oid": "6908d5b5ce3345081ade4362" }]
  },
  {
    "_id": { "$oid": "6936d957fbb35077593b128c" },
    "name": "Đùi tỏi gà giá tốt tại Bách hoá XANH",
    "sku": "dui-toi-ga-1kg",
    "image": "https://cdnv2.tgdd.vn/bhx-static/bhx/Products/Images/8790/233801/bhx/dui-toi-ga-1kg_202504121620003337.jpg",
    "category": [{ "$oid": "6908d50bce3345081ade433e" }],
    "subcategory": [{ "$oid": "6911eb361141be8e94c27cf8" }],
    "unit": "Túi",
    "unitSize": 0.3,
    "stock": 20,
    "price": 48800,
    "discount": 5,
    "description": "Mô tả sản phẩm của hệ thông bán hàng."
  },
  {
    "_id": { "$oid": "6936d957fbb35077593b128d" },
    "name": "Ổi Đài Loan giá tốt tại Bách hoá XANH",
    "sku": "oi-dai-loan-hop-1-kg",
    "image": "https://cdnv2.tgdd.vn/bhx-static/bhx/Products/Images/8788/226918/bhx/oi-dai-loan-hop-1-kg_202511031551399326.jpg",
    "category": [{ "$oid": "6908d4e8ce3345081ade433b" }],
    "unit": "Túi",
    "unitSize": 0.3,
    "stock": 15,
    "price": 16000,
    "discount": 10,
    "description": "Mô tả sản phẩm của hệ thông bán hàng.",
    "subcategory": [{ "$oid": "6908d5b5ce3345081ade4362" }]
  },
  {
    "_id": { "$oid": "6936d957fbb35077593b128e" },
    "name": "Cá diêu hồng làm sạch 500g giá rẻ tại Bách hoá XANH",
    "sku": "ca-dieu-hong-lam-sach-vi-800g",
    "image": "https://cdnv2.tgdd.vn/bhx-static/bhx/Products/Images/8782/226851/bhx/ca-dieu-hong-lam-sach-vi-800g_202505301345436899.jpg",
    "category": [{ "$oid": "6908d50bce3345081ade433e" }],
    "unit": "Túi",
    "unitSize": 0.3,
    "stock": 28,
    "price": 47000,
    "discount": 5,
    "description": "Mô tả sản phẩm của hệ thông bán hàng.",
    "subcategory": [{ "$oid": "6911ef161141be8e94c27e05" }]
  },
  {
    "_id": { "$oid": "6936d957fbb35077593b128f" },
    "name": "Thịt đùi heo giá tốt tại Bách hoá XANH",
    "sku": "thit-dui-heo-1kg",
    "image": "https://cdnv2.tgdd.vn/bhx-static/bhx/Products/Images/8781/226865/bhx/thit-dui-heo-1kg_202511041612182225.jpg",
    "category": [{ "$oid": "6908d50bce3345081ade433e" }],
    "unit": "Túi",
    "unitSize": 0.3,
    "stock": 23,
    "price": 39600,
    "discount": 10,
    "description": "Mô tả sản phẩm của hệ thông bán hàng.",
    "subcategory": [{ "$oid": "6908d541ce3345081ade434c" }]
  },
  {
    "_id": { "$oid": "6936d957fbb35077593b1290" },
    "name": "Cá nục sốt cà chua Lilly hộp 155g giá tốt tại Bách hoá XANH",
    "sku": "ca-nuc-sot-ca-lilly-hop-155g",
    "image": "https://cdnv2.tgdd.vn/bhx-static/bhx/Products/Images/3237/149420/bhx/149420_202412020846309489.png",
    "category": [{ "$oid": "6936d53bfc65c6985f8c5770" }],
    "subcategory": [{ "$oid": "6936d555fc65c6985f8c5780" }],
    "unit": "Túi",
    "unitSize": 0.3,
    "stock": 8,
    "price": 14000,
    "discount": 10,
    "description": "Mô tả sản phẩm của hệ thông bán hàng."
  },
  {
    "_id": { "$oid": "6936d957fbb35077593b1291" },
    "name": "Mì ăn liền Kang Shi Fu gà nấm hương hộp 104g Bách hóa XANH",
    "sku": "mi-an-lien-kang-shi-fu-vi-ga-nam-huong-hop-104g",
    "image": "https://www.bachhoaxanh.com/mi-an-lien-kang-shi-fu-vi-ga-nam-huong-hop-104g-202205161528585910.jpg",
    "category": [{ "$oid": "6908d33cce3345081ade4321" }],
    "unit": "Túi",
    "unitSize": 0.3,
    "stock": 22,
    "price": null,
    "discount": 0,
    "description": "Mô tả sản phẩm của hệ thông bán hàng.",
    "subcategory": [{ "$oid": "6908d8bcce3345081ade43d3" }]
  },
  {
    "_id": { "$oid": "6936d957fbb35077593b1292" },
    "name": "Bí xanh giá tốt tại Bách hoá XANH",
    "sku": "bi-xanh-tui-1kg",
    "image": "https://cdnv2.tgdd.vn/bhx-static/bhx/Products/Images/8785/233895/bhx/bi-xanh-tui-1kg_202507040912036256.jpg",
    "category": [{ "$oid": "6908d4e8ce3345081ade433b" }],
    "unit": "Túi",
    "unitSize": 0.3,
    "stock": 24,
    "price": 15000,
    "discount": 5,
    "description": "Mô tả sản phẩm của hệ thông bán hàng.",
    "subcategory": [{ "$oid": "6936d01e9bca55d5bca3016f" }]
  },
  {
    "_id": { "$oid": "6936d957fbb35077593b1293" },
    "name": "Cá thu sốt cà Vega hộp 155g | Bách hoá XANH online",
    "sku": "ca-thu-sot-ca-vega-hop-155g",
    "image": "https://cdnv2.tgdd.vn/bhx-static/bhx/Products/Images/3237/332634/bhx/thiet-ke-chua-co-ten-2024-12-31t111909314_202412311119131462.jpg",
    "category": [{ "$oid": "6936d53bfc65c6985f8c5770" }],
    "subcategory": [{ "$oid": "6936d555fc65c6985f8c5780" }],
    "unit": "Túi",
    "unitSize": 0.3,
    "stock": 14,
    "price": 15000,
    "discount": 0,
    "description": "Mô tả sản phẩm của hệ thông bán hàng."
  },
  {
    "_id": { "$oid": "6936d957fbb35077593b1294" },
    "name": "Cá basa cắt khúc 500g. giá rẻ tại Bách hoá XANH",
    "sku": "ca-basa-khuc",
    "image": "https://cdnv2.tgdd.vn/bhx-static/bhx/Products/Images/8782/309438/bhx/ca-basa-khuc_202511251705532734.jpg",
    "category": [{ "$oid": "6908d50bce3345081ade433e" }],
    "unit": "Túi",
    "unitSize": 0.3,
    "stock": 20,
    "price": 42000,
    "discount": 5,
    "description": "Mô tả sản phẩm của hệ thông bán hàng.",
    "subcategory": [{ "$oid": "6911ef161141be8e94c27e05" }]
  },
  {
    "_id": { "$oid": "6936d957fbb35077593b1295" },
    "name": "Cá hồi Coho cắt khúc nhập khẩu Chi Lê 200g tại Bách hoá XANH",
    "sku": "ca-hoi-coho-cat-khuc-nhap-khau-chi-le-200g-chi-giao-khuc-giua",
    "image": "https://cdnv2.tgdd.vn/bhx-static/bhx/Products/Images/8782/336050/bhx/ca-hoi-coho-cat-khuc-nhap-khau-chi-le-200g-chi-giao-khuc-giua_202505141644503100.jpg",
    "category": [{ "$oid": "6908d50bce3345081ade433e" }],
    "unit": "Túi",
    "unitSize": 0.3,
    "stock": 20,
    "price": 82000,
    "discount": 10,
    "description": "Mô tả sản phẩm của hệ thông bán hàng.",
    "subcategory": [{ "$oid": "6911ef161141be8e94c27e05" }]
  },
  {
    "_id": { "$oid": "6936d957fbb35077593b1296" },
    "name": "Cá hồi cắt khúc giá rẻ tại Bách hoá XANH",
    "sku": "ca-hoi-dong-lanh-cat-khuc",
    "image": "https://cdnv2.tgdd.vn/bhx-static/bhx/Products/Images/8782/309115/bhx/ca-hoi-dong-lanh-cat-khuc_202505141644048153.jpg",
    "category": [{ "$oid": "6908d50bce3345081ade433e" }],
    "unit": "Túi",
    "unitSize": 0.3,
    "stock": 15,
    "price": 90000,
    "discount": 0,
    "description": "Mô tả sản phẩm của hệ thông bán hàng.",
    "subcategory": [{ "$oid": "6911ef161141be8e94c27e05" }]
  },
  {
    "_id": { "$oid": "6936d957fbb35077593b1297" },
    "name": "Nạm bò sạch tươi ngon giá tốt tại Bách hoá XANH",
    "sku": "nam-bo-tuoi-ngon-tui-1kg",
    "image": "https://cdnv2.tgdd.vn/bhx-static/bhx/Products/Images/8139/238859/bhx/nam-bo-tuoi-ngon-tui-1kg_202512041003538471.jpg",
    "category": [{ "$oid": "6908d50bce3345081ade433e" }],
    "unit": "Túi",
    "unitSize": 0.3,
    "stock": 20,
    "price": 40400,
    "discount": 10,
    "description": "Mô tả sản phẩm của hệ thông bán hàng.",
    "subcategory": [{ "$oid": "6911ed3f1141be8e94c27d4c" }]
  },
  {
    "_id": { "$oid": "6936d957fbb35077593b1298" },
    "name": "Đầu thăn ngoại bò tuyết Mr.T 250g giá tốt tại Bách Hoá XANH",
    "sku": "dau-than-ngoai-bo-tuyet-mrt-khay-250g",
    "image": "https://cdnv2.tgdd.vn/bhx-static/bhx/Products/Images/8400/331293/bhx/2071626828-1_202411061611525939.jpg",
    "category": [{ "$oid": "6908d50bce3345081ade433e" }],
    "unit": "Túi",
    "unitSize": 0.3,
    "stock": 11,
    "price": 135000,
    "discount": 5,
    "description": "Mô tả sản phẩm của hệ thông bán hàng.",
    "subcategory": [{ "$oid": "6911ed3f1141be8e94c27d4c" }]
  },
  {
    "_id": { "$oid": "6936d957fbb35077593b1299" },
    "name": "Ba rọi heo giá tốt tại Bách hoá XANH",
    "sku": "ba-roi-heo-1kg",
    "image": "https://cdnv2.tgdd.vn/bhx-static/bhx/Products/Images/8781/226834/bhx/ba-roi-heo-1kg_202510221038422310.jpg",
    "category": [{ "$oid": "6908d50bce3345081ade433e" }],
    "unit": "Túi",
    "unitSize": 0.3,
    "stock": 19,
    "price": 50700,
    "discount": 5,
    "description": "Mô tả sản phẩm của hệ thông bán hàng.",
    "subcategory": [{ "$oid": "6908d541ce3345081ade434c" }]
  },
  {
    "_id": { "$oid": "6936d957fbb35077593b129a" },
    "name": "Dưa leo tươi 1kg giá tốt tại Bách hoá XANH",
    "sku": "dua-leo-tui-500g",
    "image": "https://cdnv2.tgdd.vn/bhx-static/bhx/Products/Images/8785/226881/bhx/dua-leo-tui-500g_202504140837248711.jpg",
    "category": [{ "$oid": "6908d4e8ce3345081ade433b" }],
    "unit": "Túi",
    "unitSize": 0.3,
    "stock": 4,
    "price": 25000,
    "discount": 10,
    "description": "Mô tả sản phẩm của hệ thông bán hàng.",
    "subcategory": [{ "$oid": "6936d01e9bca55d5bca3016f" }]
  },
  {
    "_id": { "$oid": "6936d957fbb35077593b129b" },
    "name": "Nạm bò 150g tươi ngon, giá tốt tại Bách hoá XANH",
    "sku": "nam-bo-150g-ban-le",
    "image": "https://cdnv2.tgdd.vn/bhx-static/bhx/Products/Images/8139/334237/bhx/nam-bo-150g-ban-le_202512041052380071.jpg",
    "category": [{ "$oid": "6908d50bce3345081ade433e" }],
    "unit": "Túi",
    "unitSize": 0.3,
    "stock": 10,
    "price": 27270,
    "discount": 5,
    "description": "Mô tả sản phẩm của hệ thông bán hàng.",
    "subcategory": [{ "$oid": "6911ed3f1141be8e94c27d4c" }]
  },
  {
    "_id": { "$oid": "6936d957fbb35077593b129c" },
    "name": "30 gói mì Kokomi 90 chua cay 90g giá tốt tại Bách hoá XANH",
    "sku": "thung-30-goi-mi-kokomi-90-tom-chua-cay-90g",
    "image": "https://cdnv2.tgdd.vn/bhx-static/bhx/Products/Images/2565/212760/bhx/thung-30-goi-mi-kokomi-90-tom-chua-cay-90g_202504011326552988.jpg",
    "category": [{ "$oid": "6908d33cce3345081ade4321" }],
    "unit": "Túi",
    "unitSize": 0.3,
    "stock": 25,
    "price": 120000,
    "discount": 10,
    "description": "Mô tả sản phẩm của hệ thông bán hàng.",
    "subcategory": [{ "$oid": "6908d8bcce3345081ade43d3" }]
  },
  {
    "_id": { "$oid": "6936d957fbb35077593b129d" },
    "name": "Cải ngọt khoảng 300g giá tốt tại Bách hoá XANH",
    "sku": "cai-ngot-baby-goi-300g",
    "image": "https://cdnv2.tgdd.vn/bhx-static/bhx/Products/Images/8820/223330/bhx/cai-ngot-baby-goi-300g_202506020913099833.jpg",
    "category": [{ "$oid": "6908d4e8ce3345081ade433b" }],
    "unit": "Túi",
    "unitSize": 0.3,
    "stock": 8,
    "price": 16900,
    "discount": 5,
    "description": "Mô tả sản phẩm của hệ thông bán hàng.",
    "subcategory": [{ "$oid": "6908d5bece3345081ade4366" }]
  },
  {
    "_id": { "$oid": "6936d957fbb35077593b129e" },
    "name": "Mì ăn liền vị tôm A-One gói 85g giá tốt tại Bách hoá XANH",
    "sku": "mi-a-one-tom-85g",
    "image": "https://www.bachhoaxanh.com/mi-tom-a-one-goi-85g-202205141124508285.jpg",
    "category": [{ "$oid": "6908d33cce3345081ade4321" }],
    "unit": "Túi",
    "unitSize": 0.3,
    "stock": 5,
    "price": null,
    "discount": 5,
    "description": "Mô tả sản phẩm của hệ thông bán hàng.",
    "subcategory": [{ "$oid": "6908d8bcce3345081ade43d3" }]
  },
  {
    "_id": { "$oid": "6936d957fbb35077593b129f" },
    "name": "Hành tây củ tươi ngon, giá cả cực tốt tại Bách hoá XANH",
    "sku": "hanh-tay-tui-1kg",
    "image": "https://cdnv2.tgdd.vn/bhx-static/bhx/Products/Images/8785/273076/bhx/hanh-tay-tui-1kg_202505211031332338.jpg",
    "category": [{ "$oid": "6908d4e8ce3345081ade433b" }],
    "unit": "Túi",
    "unitSize": 0.3,
    "stock": 8,
    "price": 17500,
    "discount": 10,
    "description": "Mô tả sản phẩm của hệ thông bán hàng.",
    "subcategory": [{ "$oid": "6936d01e9bca55d5bca3016f" }]
  },
  {
    "_id": { "$oid": "6936d957fbb35077593b12a0" },
    "name": "Ức gà tươi phi lê CP khay 500g giá tốt tại Bách hoá XANH",
    "sku": "uc-ga-tuoi-phi-le-khay-500g",
    "image": "https://cdnv2.tgdd.vn/bhx-static/bhx/Products/Images/8790/239600/bhx/uc-ga-tuoi-phi-le-khay-500g_202511041055113485.jpg",
    "category": [{ "$oid": "6908d50bce3345081ade433e" }],
    "subcategory": [{ "$oid": "6911eb361141be8e94c27cf8" }],
    "unit": "Túi",
    "unitSize": 0.3,
    "stock": 11,
    "price": 48790,
    "discount": 0,
    "description": "Mô tả sản phẩm của hệ thông bán hàng."
  },
  {
    "_id": { "$oid": "6936e0ba5a5094713dd15f1a" },
    "name": "Bánh cracker lúa mì AFC 8 cáix25g",
    "image": [
      "http://res.cloudinary.com/dkp3qq0mv/image/upload/v1762241804/binkeyit/qydigl8ihpjuukhvwok8.jpg",
      "http://res.cloudinary.com/dkp3qq0mv/image/upload/v1762241817/binkeyit/r6operyyrnuum77wfhaj.jpg"
    ],
    "category": [{ "$oid": "6908d3d7ce3345081ade432a" }],
    "subCategory": [{ "$oid": "6908d79ece3345081ade43af" }],
    "unit": "1 Túi",
    "unitSize": 0.3,
    "stock": 21,
    "price": 23000,
    "discount": 5,
    "description": "Bánh cracker lúa mì AFC 8 cáix25g tốt ",
    "autoCreated": false,
    "publish": true,
    "createdAt": { "$date": "2025-11-04T07:37:17.416Z" },
    "updatedAt": { "$date": "2025-11-04T07:37:17.416Z" },
    "__v": 0
  },
  {
    "_id": { "$oid": "6936e0ba5a5094713dd15f1b" },
    "name": "Nước mắm cá cơm Chinsu chai 720ml",
    "sku": "nuoc-mam-chinsu-720ml",
    "image": [
      "http://res.cloudinary.com/dkp3qq0mv/image/upload/v1762781468/binkeyit/mcd6mrsp0jvtdjebhzee.jpg"
    ],
    "category": [{ "$oid": "6908d4c0ce3345081ade4338" }],
    "subCategory": [{ "$oid": "6908d5e0ce3345081ade4371" }],
    "unit": "1 Chai",
    "unitSize": 0.3,
    "stock": 10,
    "price": 18000,
    "discount": 0,
    "description": "Nước mắm cá cơm Chinsu chai 720ml",
    "autoCreated": false,
    "publish": true,
    "createdAt": { "$date": "2025-11-10T13:32:03.167Z" },
    "updatedAt": { "$date": "2025-11-10T13:32:03.167Z" },
    "__v": 0
  },
  {
    "_id": { "$oid": "6936e0ba5a5094713dd15f1c" },
    "name": "Bánh cá vị tôm nướng Orion 35g giá tốt tại Bách hoá XANH",
    "sku": "banh-ca-orion-35g",
    "image": [
      "http://res.cloudinary.com/dkp3qq0mv/image/upload/v1762241287/binkeyit/eqxbeu2f0lnozxor7nnp.jpg",
      "http://res.cloudinary.com/dkp3qq0mv/image/upload/v1762241302/binkeyit/jl5n985bhqu9mq8qb3gw.jpg"
    ],
    "category": [{ "$oid": "6908d3d7ce3345081ade432a" }],
    "subCategory": [{ "$oid": "6908d79ece3345081ade43af" }],
    "unit": "1 Hộp ",
    "unitSize": 0.3,
    "stock": 12,
    "price": 16000,
    "discount": 2,
    "description": "Bánh cá vị tôm nướng Orion 35g giá tốt siêu ngon siêu rẻ ",
    "autoCreated": false,
    "publish": true,
    "createdAt": { "$date": "2025-11-04T07:28:59.961Z" },
    "updatedAt": { "$date": "2025-11-04T07:29:51.338Z" },
    "__v": 0,
    "more_details": {}
  },
  {
    "_id": { "$oid": "6936e0ba5a5094713dd15f1d" },
    "name": "Bánh cracker dừa sầu riêng Bibica Gooka 360g",
    "image": [
      "http://res.cloudinary.com/dkp3qq0mv/image/upload/v1762241718/binkeyit/edkr11a2aneywyigvi27.jpg",
      "http://res.cloudinary.com/dkp3qq0mv/image/upload/v1762241732/binkeyit/m9f5fsvynelmvvtqkay7.jpg"
    ],
    "category": [{ "$oid": "6908d3d7ce3345081ade432a" }],
    "subCategory": [{ "$oid": "6908d79ece3345081ade43af" }],
    "unit": "1 Hộp ",
    "unitSize": 0.3,
    "stock": 23,
    "price": 21000,
    "discount": 0,
    "description": "Bánh cracker dừa sầu riêng Bibica Gooka 360g giá siêu rẻ ",
    "autoCreated": false,
    "publish": true,
    "createdAt": { "$date": "2025-11-04T07:35:54.842Z" },
    "updatedAt": { "$date": "2025-11-04T07:35:54.842Z" },
    "__v": 0
  },
  {
    "_id": { "$oid": "6936e0ba5a5094713dd15f1e" },
    "name": "Xoài tứ quý giá tốt",
    "sku": "xoai-tu-quy",
    "image": [
      "http://res.cloudinary.com/dkp3qq0mv/image/upload/v1762781600/binkeyit/hrjq7pyawyspfzsg2wls.jpg"
    ],
    "category": [{ "$oid": "6908d4e8ce3345081ade433b" }],
    "subCategory": [{ "$oid": "6908d5b5ce3345081ade4362" }],
    "unit": "Trái",
    "unitSize": 1,
    "stock": 20,
    "price": 26000,
    "discount": 0,
    "description": "Xoài tứ quý giá tốt",
    "autoCreated": false,
    "publish": true,
    "createdAt": { "$date": "2025-11-10T13:34:13.213Z" },
    "updatedAt": { "$date": "2025-11-10T13:34:13.213Z" },
    "__v": 0
  },
  {
    "_id": { "$oid": "6936e0ba5a5094713dd15f1f" },
    "name": "Chuối già Nam Mỹ",
    "sku": "chuoi-gia-nam-mi",
    "image": [
      "http://res.cloudinary.com/dkp3qq0mv/image/upload/v1762781711/binkeyit/ssh9ivamkzvihmujpalh.jpg"
    ],
    "category": [{ "$oid": "6908d4e8ce3345081ade433b" }],
    "subCategory": [{ "$oid": "6908d5b5ce3345081ade4362" }],
    "unit": "Nải",
    "unitSize": 0.3,
    "stock": 21,
    "price": 21000,
    "discount": 1,
    "description": "Chuối già Nam Mỹ",
    "autoCreated": false,
    "publish": true,
    "createdAt": { "$date": "2025-11-10T13:35:41.353Z" },
    "updatedAt": { "$date": "2025-11-10T13:35:41.353Z" },
    "__v": 0
  },
  {
    "_id": { "$oid": "6936e0ba5a5094713dd15f20" },
    "name": "Bột giặt 2 trong 1 Funs hương hoa 900g",
    "image": [
      "http://res.cloudinary.com/dkp3qq0mv/image/upload/v1762241942/binkeyit/jvtltpuubxfrjmsi8lxf.jpg"
    ],
    "category": [{ "$oid": "6908d485ce3345081ade4333" }],
    "subCategory": [{ "$oid": "6908d681ce3345081ade4391" }],
    "unit": "1 Thùng ",
    "unitSize": 0.3,
    "stock": 21,
    "price": 390000,
    "discount": 5,
    "description": "Bột giặt 2 trong 1 Funs hương hoa 900g",
    "autoCreated": false,
    "publish": true,
    "createdAt": { "$date": "2025-11-04T07:39:25.943Z" },
    "updatedAt": { "$date": "2025-11-04T07:39:25.943Z" },
    "__v": 0
  },
  {
    "_id": { "$oid": "6936e0ba5a5094713dd15f21" },
    "name": "Ớt hiểm",
    "sku": "ot-hiem",
    "image": [
      "http://res.cloudinary.com/dkp3qq0mv/image/upload/v1762783657/binkeyit/vjncolucqz48kkijglw2.jpg"
    ],
    "category": [{ "$oid": "6908d4e8ce3345081ade433b" }],
    "subCategory": [{ "$oid": "6908d5bece3345081ade4366" }],
    "unit": "1kg ",
    "unitSize": 0.3,
    "stock": 11,
    "price": 11000,
    "discount": 0,
    "description": "bắp cải trắng ",
    "autoCreated": false,
    "publish": true,
    "createdAt": { "$date": "2025-11-10T14:08:01.321Z" },
    "updatedAt": { "$date": "2025-11-10T14:08:01.321Z" },
    "__v": 0
  },
  {
    "_id": { "$oid": "6936e0ba5a5094713dd15f22" },
    "name": "Dầu ăn hạt cải Simply chai 1 lít",
    "image": [
      "http://res.cloudinary.com/dkp3qq0mv/image/upload/v1762242428/binkeyit/gz0lpshjtns1lhg2ydwh.jpg"
    ],
    "category": [{ "$oid": "6908d4c0ce3345081ade4338" }],
    "subCategory": [{ "$oid": "6908d5d8ce3345081ade436d" }],
    "unit": "1 Chai ",
    "unitSize": 1,
    "stock": 12,
    "price": 30000,
    "discount": 0,
    "description": "Dầu ăn hạt cải Simply chai 1 lít",
    "autoCreated": false,
    "publish": true,
    "createdAt": { "$date": "2025-11-04T07:47:25.189Z" },
    "updatedAt": { "$date": "2025-11-04T07:47:25.189Z" },
    "__v": 0,
    "sku": "dau-an-simply-1lit"
  },
  {
    "_id": { "$oid": "6936e0ba5a5094713dd15f23" },
    "name": "Tiêu xanh",
    "sku": "tieu-xanh",
    "image": [
      "http://res.cloudinary.com/dkp3qq0mv/image/upload/v1762783657/binkeyit/vjncolucqz48kkijglw2.jpg"
    ],
    "category": [{ "$oid": "6908d4e8ce3345081ade433b" }],
    "subCategory": [{ "$oid": "6908d5bece3345081ade4366" }],
    "unit": "1kg ",
    "unitSize": 0.3,
    "stock": 11,
    "price": 11000,
    "discount": 0,
    "description": "bắp cải trắng ",
    "autoCreated": false,
    "publish": true,
    "createdAt": { "$date": "2025-11-10T14:08:01.321Z" },
    "updatedAt": { "$date": "2025-11-10T14:08:01.321Z" },
    "__v": 0
  },
  {
    "_id": { "$oid": "6936e0ba5a5094713dd15f24" },
    "name": "Đường ",
    "sku": "duong-tinh-luyen",
    "image": [
      "http://res.cloudinary.com/dkp3qq0mv/image/upload/v1762784246/binkeyit/jvipirfoqhjumuananvx.jpg"
    ],
    "category": [{ "$oid": "6908d4c0ce3345081ade4338" }],
    "subCategory": [{ "$oid": "6908d606ce3345081ade4379" }],
    "unit": "1kg ",
    "unitSize": 0.3,
    "stock": 12,
    "price": 12000,
    "discount": 0,
    "description": "đường ",
    "autoCreated": false,
    "publish": true,
    "createdAt": { "$date": "2025-11-10T14:17:56.502Z" },
    "updatedAt": { "$date": "2025-11-10T14:17:56.502Z" },
    "__v": 0
  },
  {
    "_id": { "$oid": "6936e0ba5a5094713dd15f25" },
    "name": "Hành ngò ",
    "sku": "hanh-ngo",
    "image": [
      "http://res.cloudinary.com/dkp3qq0mv/image/upload/v1762783599/binkeyit/s1flwns4k8b7sqv1pksj.jpg"
    ],
    "category": [{ "$oid": "6908d4e8ce3345081ade433b" }],
    "subCategory": [{ "$oid": "6908d5bece3345081ade4366" }],
    "unit": "100g",
    "unitSize": 0.3,
    "stock": 12,
    "price": 5000,
    "discount": 0,
    "description": "hành ngò ",
    "autoCreated": false,
    "publish": true,
    "createdAt": { "$date": "2025-11-10T14:07:02.991Z" },
    "updatedAt": { "$date": "2025-11-10T14:07:02.991Z" },
    "__v": 0
  },
  {
    "_id": { "$oid": "6936e0ba5a5094713dd15f26" },
    "name": "Bột ngọt ",
    "sku": "bot-ngot",
    "image": [
      "http://res.cloudinary.com/dkp3qq0mv/image/upload/v1762784294/binkeyit/av1ri9uzdiglefyiqxrx.jpg"
    ],
    "category": [{ "$oid": "6908d4c0ce3345081ade4338" }],
    "subCategory": [{ "$oid": "6908d606ce3345081ade4379" }],
    "unit": "1kg ",
    "unitSize": 0.3,
    "stock": 12,
    "price": 6000,
    "discount": 0,
    "description": "Muối sạch ",
    "autoCreated": false,
    "publish": true,
    "createdAt": { "$date": "2025-11-10T14:18:31.326Z" },
    "updatedAt": { "$date": "2025-11-10T14:18:31.326Z" },
    "__v": 0
  },
  {
    "_id": { "$oid": "6936e0ba5a5094713dd15f27" },
    "name": "Muối ",
    "sku": "muoi-iot",
    "image": [
      "http://res.cloudinary.com/dkp3qq0mv/image/upload/v1762784294/binkeyit/av1ri9uzdiglefyiqxrx.jpg"
    ],
    "category": [{ "$oid": "6908d4c0ce3345081ade4338" }],
    "subCategory": [{ "$oid": "6908d606ce3345081ade4379" }],
    "unit": "1kg ",
    "unitSize": 0.3,
    "stock": 12,
    "price": 6000,
    "discount": 0,
    "description": "Muối sạch ",
    "autoCreated": false,
    "publish": true,
    "createdAt": { "$date": "2025-11-10T14:18:31.326Z" },
    "updatedAt": { "$date": "2025-11-10T14:18:31.326Z" },
    "__v": 0
  },
  {
    "_id": { "$oid": "6936e0ba5a5094713dd15f28" },
    "name": "Dầu màu điều",
    "sku": "dau-mau-dieu",
    "image": [
      "http://res.cloudinary.com/dkp3qq0mv/image/upload/v1762784294/binkeyit/av1ri9uzdiglefyiqxrx.jpg"
    ],
    "category": [{ "$oid": "6908d4c0ce3345081ade4338" }],
    "subCategory": [{ "$oid": "6908d606ce3345081ade4379" }],
    "unit": "1kg ",
    "unitSize": 0.3,
    "stock": 12,
    "price": 6000,
    "discount": 0,
    "description": "Muối sạch ",
    "autoCreated": false,
    "publish": true,
    "createdAt": { "$date": "2025-11-10T14:18:31.326Z" },
    "updatedAt": { "$date": "2025-11-10T14:18:31.326Z" },
    "__v": 0
  },
  {
    "_id": { "$oid": "6936e0ba5a5094713dd15f29" },
    "name": "Sa tế",
    "sku": "sa-te",
    "image": [
      "http://res.cloudinary.com/dkp3qq0mv/image/upload/v1762784294/binkeyit/av1ri9uzdiglefyiqxrx.jpg"
    ],
    "category": [{ "$oid": "6908d4c0ce3345081ade4338" }],
    "subCategory": [{ "$oid": "6908d606ce3345081ade4379" }],
    "unit": "1kg ",
    "unitSize": 0.3,
    "stock": 12,
    "price": 6000,
    "discount": 0,
    "description": "Muối sạch ",
    "autoCreated": false,
    "publish": true,
    "createdAt": { "$date": "2025-11-10T14:18:31.326Z" },
    "updatedAt": { "$date": "2025-11-10T14:18:31.326Z" },
    "__v": 0
  },
  {
    "_id": { "$oid": "6936e0ba5a5094713dd15f2a" },
    "name": "Chanh không hạt",
    "sku": "chanh-khong-hat",
    "image": [
      "http://res.cloudinary.com/dkp3qq0mv/image/upload/v1762784294/binkeyit/av1ri9uzdiglefyiqxrx.jpg"
    ],
    "category": [{ "$oid": "6908d4c0ce3345081ade4338" }],
    "subCategory": [{ "$oid": "6908d606ce3345081ade4379" }],
    "unit": "1kg ",
    "unitSize": 0.3,
    "stock": 12,
    "price": 6000,
    "discount": 0,
    "description": "Muối sạch ",
    "autoCreated": false,
    "publish": true,
    "createdAt": { "$date": "2025-11-10T14:18:31.326Z" }
  },
  {
    "_id": { "$oid": "6936e0ba5a5094713dd15f2b" },
    "name": "Hạt nêm knor ",
    "sku": "hat-nem-knor",
    "image": [
      "http://res.cloudinary.com/dkp3qq0mv/image/upload/v1762784333/binkeyit/n2lrtdqk2psfs7ejh8yh.jpg"
    ],
    "category": [{ "$oid": "6908d4c0ce3345081ade4338" }],
    "subCategory": [{ "$oid": "6908d606ce3345081ade4379" }],
    "unit": "200g ",
    "unitSize": 0.3,
    "stock": 12,
    "price": 16000,
    "discount": 0,
    "description": "hạt nêm ",
    "autoCreated": false,
    "publish": true,
    "createdAt": { "$date": "2025-11-10T14:19:24.492Z" }
  },
  {
    "_id": { "$oid": "6936e0ba5a5094713dd15f2c" },
    "name": "Tiêu đen",
    "sku": "tieu-den",
    "image": [
      "http://res.cloudinary.com/dkp3qq0mv/image/upload/v1762784420/binkeyit/okdpicoapkkg7jnf1amn.jpg"
    ],
    "category": [{ "$oid": "6908d4c0ce3345081ade4338" }],
    "subCategory": [{ "$oid": "6908d626ce3345081ade437d" }],
    "unit": "50g ",
    "unitSize": 0.3,
    "stock": 12,
    "price": 24000,
    "discount": 0,
    "description": "tiêu ",
    "autoCreated": false,
    "publish": true,
    "createdAt": { "$date": "2025-11-10T14:20:42.725Z" },
    "updatedAt": { "$date": "2025-11-10T14:25:27.081Z" },
    "__v": 0
  },
  {
    "_id": { "$oid": "6936e0ba5a5094713dd15f2d" },
    "name": "Thùng 48 hộp sữa ít đường Vinamilk ADM 180ml",
    "image": [
      "http://res.cloudinary.com/dkp3qq0mv/image/upload/v1762242143/binkeyit/yanf4lj7k2ouvjskv4z8.jpg"
    ],
    "category": [{ "$oid": "6908d36fce3345081ade4324" }],
    "subCategory": [{ "$oid": "6908d87ece3345081ade43cc" }],
    "unit": "1 Thùng ",
    "unitSize": 0.3,
    "stock": 33,
    "price": 330000,
    "discount": 0,
    "description": "Thùng 48 hộp sữa ít đường Vinamilk ADM 180ml",
    "autoCreated": false,
    "publish": true,
    "createdAt": { "$date": "2025-11-04T07:42:48.778Z" },
    "updatedAt": { "$date": "2025-11-04T07:42:48.778Z" },
    "__v": 0
  },
  {
    "_id": { "$oid": "6936e0ba5a5094713dd15f2e" },
    "name": "Ớt say ",
    "sku": "ot-say",
    "image": [
      "http://res.cloudinary.com/dkp3qq0mv/image/upload/v1762784382/binkeyit/pirn5s7of3jthfl0wvay.jpg"
    ],
    "category": [{ "$oid": "6908d4c0ce3345081ade4338" }],
    "subCategory": [{ "$oid": "6908d626ce3345081ade437d" }],
    "unit": "1 chai ",
    "unitSize": 0.3,
    "stock": 12,
    "price": 13000,
    "discount": 1,
    "description": "ớt ",
    "autoCreated": false,
    "publish": true,
    "createdAt": { "$date": "2025-11-10T14:20:01.365Z" },
    "updatedAt": { "$date": "2025-11-10T14:25:27.081Z" },
    "__v": 0
  },
  {
    "_id": { "$oid": "6936e0ba5a5094713dd15f2f" },
    "name": "Bột nghệ ",
    "sku": "bot-nghe",
    "image": [
      "http://res.cloudinary.com/dkp3qq0mv/image/upload/v1762784463/binkeyit/iqb4p63nkjcefne8jfq0.jpg"
    ],
    "category": [{ "$oid": "6908d4c0ce3345081ade4338" }],
    "subCategory": [{ "$oid": "6908d626ce3345081ade437d" }],
    "unit": "32g ",
    "unitSize": 0.3,
    "stock": 12,
    "price": 30000,
    "discount": 0,
    "description": "nghệ ",
    "autoCreated": false,
    "publish": true,
    "createdAt": { "$date": "2025-11-10T14:21:22.044Z" },
    "updatedAt": { "$date": "2025-11-10T14:25:27.081Z" },
    "__v": 0
  },
  {
    "_id": { "$oid": "6936e0ba5a5094713dd15f30" },
    "name": "Mì ăn liền Kang Shi Fu gà nấm hương",
    "sku": "mi-an-lien-kangshifu-6goi",
    "image": [
      "http://res.cloudinary.com/dkp3qq0mv/image/upload/v1762780779/binkeyit/odk0jbjayfbhr1agbexg.jpg"
    ],
    "category": [{ "$oid": "6908d33cce3345081ade4321" }],
    "subCategory": [{ "$oid": "6908d8bcce3345081ade43d3" }],
    "unit": "1 hộp",
    "unitSize": 0.3,
    "stock": 14,
    "price": 15000,
    "discount": 0,
    "description": "Mì ăn liền Kang Shi Fu gà nấm hương",
    "autoCreated": false,
    "publish": true,
    "createdAt": { "$date": "2025-11-10T13:20:02.355Z" },
    "updatedAt": { "$date": "2025-11-10T13:20:02.355Z" },
    "__v": 0
  },
  {
    "_id": { "$oid": "6936e0ba5a5094713dd15f31" },
    "name": "Thùng 24 lon nước tăng lực Rockstar 250ml",
    "image": [
      "http://res.cloudinary.com/dkp3qq0mv/image/upload/v1762242211/binkeyit/r0xctsuyyktvafgon6gn.jpg",
      "http://res.cloudinary.com/dkp3qq0mv/image/upload/v1762242223/binkeyit/ggnvsn4eorvxfy0oxglr.jpg"
    ],
    "category": [{ "$oid": "6908d3b3ce3345081ade4327" }],
    "subCategory": [{ "$oid": "6908d80ece3345081ade43c1" }],
    "unit": "1 Thùng",
    "unitSize": 0.3,
    "stock": 23,
    "price": 345000,
    "discount": 0,
    "description": "Thùng 24 lon nước tăng lực Rockstar 250ml",
    "autoCreated": false,
    "publish": true,
    "createdAt": { "$date": "2025-11-04T07:44:06.022Z" },
    "updatedAt": { "$date": "2025-11-04T07:44:06.022Z" },
    "__v": 0
  },
  {
    "_id": { "$oid": "6936e0ba5a5094713dd15f32" },
    "name": "Thùng 24 lon Sài Gòn Lager 330ml",
    "image": [
      "http://res.cloudinary.com/dkp3qq0mv/image/upload/v1762242015/binkeyit/dulbjqf6ogdckm6yeci5.jpg"
    ],
    "category": [{ "$oid": "6908d3b3ce3345081ade4327" }],
    "subCategory": [{ "$oid": "6908d7e1ce3345081ade43b9" }],
    "unit": "1 Thùng ",
    "unitSize": 0.3,
    "stock": 33,
    "price": 450000,
    "discount": 5,
    "description": "Thùng 24 lon Sài Gòn Lager 330ml",
    "autoCreated": false,
    "publish": true,
    "createdAt": { "$date": "2025-11-04T07:40:40.853Z" },
    "updatedAt": { "$date": "2025-11-04T07:40:40.853Z" },
    "__v": 0
  },
  {
    "_id": { "$oid": "6936e0ba5a5094713dd15f33" },
    "name": "Thùng 24 lon Redbull Thái kẽm 250ml",
    "image": [
      "http://res.cloudinary.com/dkp3qq0mv/image/upload/v1762242065/binkeyit/qjnuwa7y3s4mukaj8yxp.jpg",
      "http://res.cloudinary.com/dkp3qq0mv/image/upload/v1762242081/binkeyit/jiyxrooangngxs6bcwon.jpg"
    ],
    "category": [{ "$oid": "6908d3b3ce3345081ade4327" }],
    "subCategory": [{ "$oid": "6908d80ece3345081ade43c1" }],
    "unit": "1 Thùng ",
    "unitSize": 0.3,
    "stock": 12,
    "price": 550000,
    "discount": 2,
    "description": "Thùng 24 lon Redbull Thái kẽm 250ml",
    "autoCreated": false,
    "publish": true,
    "createdAt": { "$date": "2025-11-04T07:41:39.548Z" },
    "updatedAt": { "$date": "2025-11-04T07:41:39.548Z" },
    "__v": 0
  },
  {
    "_id": { "$oid": "6936e0ba5a5094713dd15f34" },
    "name": "Lốc 5 gói bún giò heo Hằng Nga 75g",
    "sku": "bun-gio-heo-hang-nga-75g",
    "image": [
      "http://res.cloudinary.com/dkp3qq0mv/image/upload/v1762780878/binkeyit/umo11ol2nt0eudkjiorg.jpg"
    ],
    "category": [{ "$oid": "6908d33cce3345081ade4321" }],
    "subCategory": [{ "$oid": "6908d8e8ce3345081ade43d7" }],
    "unit": "5 gói ",
    "unitSize": 5,
    "stock": 34,
    "price": 60000,
    "discount": 0,
    "description": "Lốc 5 gói bún giò heo Hằng Nga 75g",
    "autoCreated": false,
    "publish": true,
    "createdAt": { "$date": "2025-11-10T13:26:51.982Z" },
    "updatedAt": { "$date": "2025-11-10T13:26:51.982Z" },
    "__v": 0
  },
  {
    "_id": { "$oid": "6936e0ba5a5094713dd15f35" },
    "name": "Thùng 24 chai nước khoáng La Vie 500ml ",
    "image": [
      "http://res.cloudinary.com/dkp3qq0mv/image/upload/v1762242299/binkeyit/kz3ygimvfp4uooem8wex.jpg",
      "http://res.cloudinary.com/dkp3qq0mv/image/upload/v1762242318/binkeyit/l6hhc3gcxxopiytvypme.jpg"
    ],
    "category": [{ "$oid": "6908d3b3ce3345081ade4327" }],
    "subCategory": [{ "$oid": "6908d831ce3345081ade43c5" }],
    "unit": "1 Thùng ",
    "unitSize": 0.3,
    "stock": 12,
    "price": 60000,
    "discount": 0,
    "description": "Thùng 24 chai nước khoáng La Vie 500ml ",
    "autoCreated": false,
    "publish": true,
    "createdAt": { "$date": "2025-11-04T07:45:39.371Z" },
    "updatedAt": { "$date": "2025-11-04T07:45:39.371Z" },
    "__v": 0
  },
  {
    "_id": { "$oid": "6936e0ba5a5094713dd15f36" },
    "sku": "olon-tea-plus-450ml",
    "__v": 0,
    "autoCreated": true,
    "category": [{ "$oid": "6908d3b3ce3345081ade4327" }],
    "createdAt": { "$date": "2025-11-04T08:29:32.753Z" },
    "description": "1 Thùng 12 cchai olong tea plus.",
    "discount": 10,
    "image": ["TeaPlus_1.jpg"],
    "more_details": { "brand": "Orion" },
    "name": "Trà Olong Tea Plus",
    "price": 12000,
    "publish": true,
    "stock": 6,
    "subCategory": [{ "$oid": "6908d80ece3345081ade43c1" }],
    "unit": "12 Chai",
    "unitSize": 0.3,
    "updatedAt": { "$date": "2025-11-04T10:09:18.92Z" }
  },
  {
    "_id": { "$oid": "6936e0ba5a5094713dd15f37" },
    "sku": "revive-chanh-muoi-500ml",
    "__v": 0,
    "autoCreated": true,
    "category": [{ "$oid": "6908d3b3ce3345081ade4327" }],
    "createdAt": { "$date": "2025-11-04T08:37:38.799Z" },
    "description": "Nước chanh muốimới",
    "discount": 0,
    "image": ["revive.jpeg"],
    "more_details": { "brand": "Revive" },
    "name": "Revive Chanh Muối 500ml",
    "price": 12000,
    "publish": true,
    "stock": 20,
    "subCategory": [{ "$oid": "6908d80ece3345081ade43c1" }],
    "unit": "500 ml",
    "unitSize": 1,
    "updatedAt": { "$date": "2025-11-04T09:41:13.279Z" }
  },
  {
    "_id": { "$oid": "6936e0ba5a5094713dd15f38" },
    "name": "Dầu ăn thượng hạng Neptune 1 lít",
    "sku": "dau-an-neptune-1l",
    "image": [
      "http://res.cloudinary.com/dkp3qq0mv/image/upload/v1762780599/binkeyit/zubhdsfrb4kvyom37ttm.jpg"
    ],
    "category": [{ "$oid": "6908d4c0ce3345081ade4338" }],
    "subCategory": [{ "$oid": "6908d5d8ce3345081ade436d" }],
    "unit": "1 l",
    "unitSize": 1,
    "stock": 12,
    "price": 34000,
    "discount": 0,
    "description": "Dầu ăn thượng hạng Neptune 1 lít",
    "autoCreated": false,
    "publish": true,
    "createdAt": { "$date": "2025-11-10T13:16:58.39Z" },
    "updatedAt": { "$date": "2025-11-10T13:16:58.39Z" },
    "__v": 0
  },
  {
    "_id": { "$oid": "6936e0ba5a5094713dd15f39" },
    "name": "Dầu đậu nành Janbee chai 1 lít",
    "sku": "dau-an-janbee-1l",
    "image": [
      "http://res.cloudinary.com/dkp3qq0mv/image/upload/v1762780657/binkeyit/uxm0jgntymplksaywca9.jpg"
    ],
    "category": [{ "$oid": "6908d4c0ce3345081ade4338" }],
    "subCategory": [{ "$oid": "6908d5d8ce3345081ade436d" }],
    "unit": "1 l",
    "unitSize": 1,
    "stock": 12,
    "price": 39000,
    "discount": 2,
    "description": "Dầu đậu nành Janbee chai 1 lít",
    "autoCreated": false,
    "publish": true,
    "createdAt": { "$date": "2025-11-10T13:18:03.108Z" },
    "updatedAt": { "$date": "2025-11-10T13:18:03.108Z" },
    "__v": 0
  }
]
